[
    {
        "code_station": "01097000",
        "libelle_station": "LA TERNOISE \u00c0 AUCHY LES HESDIN (62)",
        "localisation": "PONT DU CD 123",
        "uri_station": "https:\/\/id.eaufrance.fr\/StationMesureEauxSurface\/01097000",
        "longitude": 2.1026201,
        "latitude": 50.397567967,
        "code_commune": "62050",
        "libelle_commune": "Auchy-l\u00e8s-Hesdin",
        "code_cours_eau": "E5400650",
        "libelle_cours_eau": "Ternoise",
        "uri_cours_eau": "https:\/\/id.eaufrance.fr\/CoursEau_Carthage2017\/E5400650",
        "date_mesure_temp": "2009-09-14",
        "heure_mesure_temp": "17:00:00",
        "resultat": 12.485
    },
    {
        "code_station": "01097000",
        "libelle_station": "LA TERNOISE \u00c0 AUCHY LES HESDIN (62)",
        "localisation": "PONT DU CD 123",
        "uri_station": "https:\/\/id.eaufrance.fr\/StationMesureEauxSurface\/01097000",
        "longitude": 2.1026201,
        "latitude": 50.397567967,
        "code_commune": "62050",
        "libelle_commune": "Auchy-l\u00e8s-Hesdin",
        "code_cours_eau": "E5400650",
        "libelle_cours_eau": "Ternoise",
        "uri_cours_eau": "https:\/\/id.eaufrance.fr\/CoursEau_Carthage2017\/E5400650",
        "date_mesure_temp": "2009-10-01",
        "heure_mesure_temp": "00:00:00",
        "resultat": 12.195
    },
    {
        "code_station": "01097000",
        "libelle_station": "LA TERNOISE \u00c0 AUCHY LES HESDIN (62)",
        "localisation": "PONT DU CD 123",
        "uri_station": "https:\/\/id.eaufrance.fr\/StationMesureEauxSurface\/01097000",
        "longitude": 2.1026201,
        "latitude": 50.397567967,
        "code_commune": "62050",
        "libelle_commune": "Auchy-l\u00e8s-Hesdin",
        "code_cours_eau": "E5400650",
        "libelle_cours_eau": "Ternoise",
        "uri_cours_eau": "https:\/\/id.eaufrance.fr\/CoursEau_Carthage2017\/E5400650",
        "date_mesure_temp": "2009-11-01",
        "heure_mesure_temp": "00:00:00",
        "resultat": 11.053
    },
    {
        "code_station": "01097000",
        "libelle_station": "LA TERNOISE \u00c0 AUCHY LES HESDIN (62)",
        "localisation": "PONT DU CD 123",
        "uri_station": "https:\/\/id.eaufrance.fr\/StationMesureEauxSurface\/01097000",
        "longitude": 2.1026201,
        "latitude": 50.397567967,
        "code_commune": "62050",
        "libelle_commune": "Auchy-l\u00e8s-Hesdin",
        "code_cours_eau": "E5400650",
        "libelle_cours_eau": "Ternoise",
        "uri_cours_eau": "https:\/\/id.eaufrance.fr\/CoursEau_Carthage2017\/E5400650",
        "date_mesure_temp": "2009-12-01",
        "heure_mesure_temp": "00:00:00",
        "resultat": 9.854
    },
    {
        "code_station": "01097000",
        "libelle_station": "LA TERNOISE \u00c0 AUCHY LES HESDIN (62)",
        "localisation": "PONT DU CD 123",
        "uri_station": "https:\/\/id.eaufrance.fr\/StationMesureEauxSurface\/01097000",
        "longitude": 2.1026201,
        "latitude": 50.397567967,
        "code_commune": "62050",
        "libelle_commune": "Auchy-l\u00e8s-Hesdin",
        "code_cours_eau": "E5400650",
        "libelle_cours_eau": "Ternoise",
        "uri_cours_eau": "https:\/\/id.eaufrance.fr\/CoursEau_Carthage2017\/E5400650",
        "date_mesure_temp": "2010-01-01",
        "heure_mesure_temp": "00:00:00",
        "resultat": 8.965
    },
    {
        "code_station": "01097000",
        "libelle_station": "LA TERNOISE \u00c0 AUCHY LES HESDIN (62)",
        "localisation": "PONT DU CD 123",
        "uri_station": "https:\/\/id.eaufrance.fr\/StationMesureEauxSurface\/01097000",
        "longitude": 2.1026201,
        "latitude": 50.397567967,
        "code_commune": "62050",
        "libelle_commune": "Auchy-l\u00e8s-Hesdin",
        "code_cours_eau": "E5400650",
        "libelle_cours_eau": "Ternoise",
        "uri_cours_eau": "https:\/\/id.eaufrance.fr\/CoursEau_Carthage2017\/E5400650",
        "date_mesure_temp": "2010-02-01",
        "heure_mesure_temp": "00:00:00",
        "resultat": 8.17
    },
    {
        "code_station": "01097000",
        "libelle_station": "LA TERNOISE \u00c0 AUCHY LES HESDIN (62)",
        "localisation": "PONT DU CD 123",
        "uri_station": "https:\/\/id.eaufrance.fr\/StationMesureEauxSurface\/01097000",
        "longitude": 2.1026201,
        "latitude": 50.397567967,
        "code_commune": "62050",
        "libelle_commune": "Auchy-l\u00e8s-Hesdin",
        "code_cours_eau": "E5400650",
        "libelle_cours_eau": "Ternoise",
        "uri_cours_eau": "https:\/\/id.eaufrance.fr\/CoursEau_Carthage2017\/E5400650",
        "date_mesure_temp": "2010-03-01",
        "heure_mesure_temp": "00:00:00",
        "resultat": 9.139
    },
    {
        "code_station": "01097000",
        "libelle_station": "LA TERNOISE \u00c0 AUCHY LES HESDIN (62)",
        "localisation": "PONT DU CD 123",
        "uri_station": "https:\/\/id.eaufrance.fr\/StationMesureEauxSurface\/01097000",
        "longitude": 2.1026201,
        "latitude": 50.397567967,
        "code_commune": "62050",
        "libelle_commune": "Auchy-l\u00e8s-Hesdin",
        "code_cours_eau": "E5400650",
        "libelle_cours_eau": "Ternoise",
        "uri_cours_eau": "https:\/\/id.eaufrance.fr\/CoursEau_Carthage2017\/E5400650",
        "date_mesure_temp": "2010-04-01",
        "heure_mesure_temp": "00:00:00",
        "resultat": 9.558
    },
    {
        "code_station": "01097000",
        "libelle_station": "LA TERNOISE \u00c0 AUCHY LES HESDIN (62)",
        "localisation": "PONT DU CD 123",
        "uri_station": "https:\/\/id.eaufrance.fr\/StationMesureEauxSurface\/01097000",
        "longitude": 2.1026201,
        "latitude": 50.397567967,
        "code_commune": "62050",
        "libelle_commune": "Auchy-l\u00e8s-Hesdin",
        "code_cours_eau": "E5400650",
        "libelle_cours_eau": "Ternoise",
        "uri_cours_eau": "https:\/\/id.eaufrance.fr\/CoursEau_Carthage2017\/E5400650",
        "date_mesure_temp": "2010-05-01",
        "heure_mesure_temp": "00:00:00",
        "resultat": 11.904
    },
    {
        "code_station": "01097000",
        "libelle_station": "LA TERNOISE \u00c0 AUCHY LES HESDIN (62)",
        "localisation": "PONT DU CD 123",
        "uri_station": "https:\/\/id.eaufrance.fr\/StationMesureEauxSurface\/01097000",
        "longitude": 2.1026201,
        "latitude": 50.397567967,
        "code_commune": "62050",
        "libelle_commune": "Auchy-l\u00e8s-Hesdin",
        "code_cours_eau": "E5400650",
        "libelle_cours_eau": "Ternoise",
        "uri_cours_eau": "https:\/\/id.eaufrance.fr\/CoursEau_Carthage2017\/E5400650",
        "date_mesure_temp": "2010-06-01",
        "heure_mesure_temp": "00:00:00",
        "resultat": 11.346
    },
    {
        "code_station": "01097000",
        "libelle_station": "LA TERNOISE \u00c0 AUCHY LES HESDIN (62)",
        "localisation": "PONT DU CD 123",
        "uri_station": "https:\/\/id.eaufrance.fr\/StationMesureEauxSurface\/01097000",
        "longitude": 2.1026201,
        "latitude": 50.397567967,
        "code_commune": "62050",
        "libelle_commune": "Auchy-l\u00e8s-Hesdin",
        "code_cours_eau": "E5400650",
        "libelle_cours_eau": "Ternoise",
        "uri_cours_eau": "https:\/\/id.eaufrance.fr\/CoursEau_Carthage2017\/E5400650",
        "date_mesure_temp": "2010-07-01",
        "heure_mesure_temp": "00:00:00",
        "resultat": 14.337
    },
    {
        "code_station": "01097000",
        "libelle_station": "LA TERNOISE \u00c0 AUCHY LES HESDIN (62)",
        "localisation": "PONT DU CD 123",
        "uri_station": "https:\/\/id.eaufrance.fr\/StationMesureEauxSurface\/01097000",
        "longitude": 2.1026201,
        "latitude": 50.397567967,
        "code_commune": "62050",
        "libelle_commune": "Auchy-l\u00e8s-Hesdin",
        "code_cours_eau": "E5400650",
        "libelle_cours_eau": "Ternoise",
        "uri_cours_eau": "https:\/\/id.eaufrance.fr\/CoursEau_Carthage2017\/E5400650",
        "date_mesure_temp": "2010-08-01",
        "heure_mesure_temp": "00:00:00",
        "resultat": 12.847
    },
    {
        "code_station": "01097000",
        "libelle_station": "LA TERNOISE \u00c0 AUCHY LES HESDIN (62)",
        "localisation": "PONT DU CD 123",
        "uri_station": "https:\/\/id.eaufrance.fr\/StationMesureEauxSurface\/01097000",
        "longitude": 2.1026201,
        "latitude": 50.397567967,
        "code_commune": "62050",
        "libelle_commune": "Auchy-l\u00e8s-Hesdin",
        "code_cours_eau": "E5400650",
        "libelle_cours_eau": "Ternoise",
        "uri_cours_eau": "https:\/\/id.eaufrance.fr\/CoursEau_Carthage2017\/E5400650",
        "date_mesure_temp": "2010-09-01",
        "heure_mesure_temp": "00:00:00",
        "resultat": 11.783
    },
    {
        "code_station": "01097000",
        "libelle_station": "LA TERNOISE \u00c0 AUCHY LES HESDIN (62)",
        "localisation": "PONT DU CD 123",
        "uri_station": "https:\/\/id.eaufrance.fr\/StationMesureEauxSurface\/01097000",
        "longitude": 2.1026201,
        "latitude": 50.397567967,
        "code_commune": "62050",
        "libelle_commune": "Auchy-l\u00e8s-Hesdin",
        "code_cours_eau": "E5400650",
        "libelle_cours_eau": "Ternoise",
        "uri_cours_eau": "https:\/\/id.eaufrance.fr\/CoursEau_Carthage2017\/E5400650",
        "date_mesure_temp": "2010-10-01",
        "heure_mesure_temp": "00:00:00",
        "resultat": 11.516
    },
    {
        "code_station": "01097000",
        "libelle_station": "LA TERNOISE \u00c0 AUCHY LES HESDIN (62)",
        "localisation": "PONT DU CD 123",
        "uri_station": "https:\/\/id.eaufrance.fr\/StationMesureEauxSurface\/01097000",
        "longitude": 2.1026201,
        "latitude": 50.397567967,
        "code_commune": "62050",
        "libelle_commune": "Auchy-l\u00e8s-Hesdin",
        "code_cours_eau": "E5400650",
        "libelle_cours_eau": "Ternoise",
        "uri_cours_eau": "https:\/\/id.eaufrance.fr\/CoursEau_Carthage2017\/E5400650",
        "date_mesure_temp": "2010-11-01",
        "heure_mesure_temp": "00:00:00",
        "resultat": 10.883
    },
    {
        "code_station": "01097000",
        "libelle_station": "LA TERNOISE \u00c0 AUCHY LES HESDIN (62)",
        "localisation": "PONT DU CD 123",
        "uri_station": "https:\/\/id.eaufrance.fr\/StationMesureEauxSurface\/01097000",
        "longitude": 2.1026201,
        "latitude": 50.397567967,
        "code_commune": "62050",
        "libelle_commune": "Auchy-l\u00e8s-Hesdin",
        "code_cours_eau": "E5400650",
        "libelle_cours_eau": "Ternoise",
        "uri_cours_eau": "https:\/\/id.eaufrance.fr\/CoursEau_Carthage2017\/E5400650",
        "date_mesure_temp": "2010-12-01",
        "heure_mesure_temp": "00:00:00",
        "resultat": 6.94
    },
    {
        "code_station": "01097000",
        "libelle_station": "LA TERNOISE \u00c0 AUCHY LES HESDIN (62)",
        "localisation": "PONT DU CD 123",
        "uri_station": "https:\/\/id.eaufrance.fr\/StationMesureEauxSurface\/01097000",
        "longitude": 2.1026201,
        "latitude": 50.397567967,
        "code_commune": "62050",
        "libelle_commune": "Auchy-l\u00e8s-Hesdin",
        "code_cours_eau": "E5400650",
        "libelle_cours_eau": "Ternoise",
        "uri_cours_eau": "https:\/\/id.eaufrance.fr\/CoursEau_Carthage2017\/E5400650",
        "date_mesure_temp": "2011-01-01",
        "heure_mesure_temp": "00:00:00",
        "resultat": 8.12
    },
    {
        "code_station": "01097000",
        "libelle_station": "LA TERNOISE \u00c0 AUCHY LES HESDIN (62)",
        "localisation": "PONT DU CD 123",
        "uri_station": "https:\/\/id.eaufrance.fr\/StationMesureEauxSurface\/01097000",
        "longitude": 2.1026201,
        "latitude": 50.397567967,
        "code_commune": "62050",
        "libelle_commune": "Auchy-l\u00e8s-Hesdin",
        "code_cours_eau": "E5400650",
        "libelle_cours_eau": "Ternoise",
        "uri_cours_eau": "https:\/\/id.eaufrance.fr\/CoursEau_Carthage2017\/E5400650",
        "date_mesure_temp": "2011-02-01",
        "heure_mesure_temp": "00:00:00",
        "resultat": 7.142
    },
    {
        "code_station": "01097000",
        "libelle_station": "LA TERNOISE \u00c0 AUCHY LES HESDIN (62)",
        "localisation": "PONT DU CD 123",
        "uri_station": "https:\/\/id.eaufrance.fr\/StationMesureEauxSurface\/01097000",
        "longitude": 2.1026201,
        "latitude": 50.397567967,
        "code_commune": "62050",
        "libelle_commune": "Auchy-l\u00e8s-Hesdin",
        "code_cours_eau": "E5400650",
        "libelle_cours_eau": "Ternoise",
        "uri_cours_eau": "https:\/\/id.eaufrance.fr\/CoursEau_Carthage2017\/E5400650",
        "date_mesure_temp": "2011-03-01",
        "heure_mesure_temp": "00:00:00",
        "resultat": 8.543
    },
    {
        "code_station": "01097000",
        "libelle_station": "LA TERNOISE \u00c0 AUCHY LES HESDIN (62)",
        "localisation": "PONT DU CD 123",
        "uri_station": "https:\/\/id.eaufrance.fr\/StationMesureEauxSurface\/01097000",
        "longitude": 2.1026201,
        "latitude": 50.397567967,
        "code_commune": "62050",
        "libelle_commune": "Auchy-l\u00e8s-Hesdin",
        "code_cours_eau": "E5400650",
        "libelle_cours_eau": "Ternoise",
        "uri_cours_eau": "https:\/\/id.eaufrance.fr\/CoursEau_Carthage2017\/E5400650",
        "date_mesure_temp": "2011-04-01",
        "heure_mesure_temp": "00:00:00",
        "resultat": 11.2
    },
    {
        "code_station": "01097000",
        "libelle_station": "LA TERNOISE \u00c0 AUCHY LES HESDIN (62)",
        "localisation": "PONT DU CD 123",
        "uri_station": "https:\/\/id.eaufrance.fr\/StationMesureEauxSurface\/01097000",
        "longitude": 2.1026201,
        "latitude": 50.397567967,
        "code_commune": "62050",
        "libelle_commune": "Auchy-l\u00e8s-Hesdin",
        "code_cours_eau": "E5400650",
        "libelle_cours_eau": "Ternoise",
        "uri_cours_eau": "https:\/\/id.eaufrance.fr\/CoursEau_Carthage2017\/E5400650",
        "date_mesure_temp": "2011-05-01",
        "heure_mesure_temp": "00:00:00",
        "resultat": 12.799
    },
    {
        "code_station": "01097000",
        "libelle_station": "LA TERNOISE \u00c0 AUCHY LES HESDIN (62)",
        "localisation": "PONT DU CD 123",
        "uri_station": "https:\/\/id.eaufrance.fr\/StationMesureEauxSurface\/01097000",
        "longitude": 2.1026201,
        "latitude": 50.397567967,
        "code_commune": "62050",
        "libelle_commune": "Auchy-l\u00e8s-Hesdin",
        "code_cours_eau": "E5400650",
        "libelle_cours_eau": "Ternoise",
        "uri_cours_eau": "https:\/\/id.eaufrance.fr\/CoursEau_Carthage2017\/E5400650",
        "date_mesure_temp": "2011-06-01",
        "heure_mesure_temp": "00:00:00",
        "resultat": 12.871
    },
    {
        "code_station": "01097000",
        "libelle_station": "LA TERNOISE \u00c0 AUCHY LES HESDIN (62)",
        "localisation": "PONT DU CD 123",
        "uri_station": "https:\/\/id.eaufrance.fr\/StationMesureEauxSurface\/01097000",
        "longitude": 2.1026201,
        "latitude": 50.397567967,
        "code_commune": "62050",
        "libelle_commune": "Auchy-l\u00e8s-Hesdin",
        "code_cours_eau": "E5400650",
        "libelle_cours_eau": "Ternoise",
        "uri_cours_eau": "https:\/\/id.eaufrance.fr\/CoursEau_Carthage2017\/E5400650",
        "date_mesure_temp": "2011-07-01",
        "heure_mesure_temp": "00:00:00",
        "resultat": 14.122
    },
    {
        "code_station": "01097000",
        "libelle_station": "LA TERNOISE \u00c0 AUCHY LES HESDIN (62)",
        "localisation": "PONT DU CD 123",
        "uri_station": "https:\/\/id.eaufrance.fr\/StationMesureEauxSurface\/01097000",
        "longitude": 2.1026201,
        "latitude": 50.397567967,
        "code_commune": "62050",
        "libelle_commune": "Auchy-l\u00e8s-Hesdin",
        "code_cours_eau": "E5400650",
        "libelle_cours_eau": "Ternoise",
        "uri_cours_eau": "https:\/\/id.eaufrance.fr\/CoursEau_Carthage2017\/E5400650",
        "date_mesure_temp": "2011-08-01",
        "heure_mesure_temp": "00:00:00",
        "resultat": 13.473
    },
    {
        "code_station": "01097000",
        "libelle_station": "LA TERNOISE \u00c0 AUCHY LES HESDIN (62)",
        "localisation": "PONT DU CD 123",
        "uri_station": "https:\/\/id.eaufrance.fr\/StationMesureEauxSurface\/01097000",
        "longitude": 2.1026201,
        "latitude": 50.397567967,
        "code_commune": "62050",
        "libelle_commune": "Auchy-l\u00e8s-Hesdin",
        "code_cours_eau": "E5400650",
        "libelle_cours_eau": "Ternoise",
        "uri_cours_eau": "https:\/\/id.eaufrance.fr\/CoursEau_Carthage2017\/E5400650",
        "date_mesure_temp": "2011-09-01",
        "heure_mesure_temp": "00:00:00",
        "resultat": 12.243
    },
    {
        "code_station": "01097000",
        "libelle_station": "LA TERNOISE \u00c0 AUCHY LES HESDIN (62)",
        "localisation": "PONT DU CD 123",
        "uri_station": "https:\/\/id.eaufrance.fr\/StationMesureEauxSurface\/01097000",
        "longitude": 2.1026201,
        "latitude": 50.397567967,
        "code_commune": "62050",
        "libelle_commune": "Auchy-l\u00e8s-Hesdin",
        "code_cours_eau": "E5400650",
        "libelle_cours_eau": "Ternoise",
        "uri_cours_eau": "https:\/\/id.eaufrance.fr\/CoursEau_Carthage2017\/E5400650",
        "date_mesure_temp": "2011-10-01",
        "heure_mesure_temp": "00:00:00",
        "resultat": 12.944
    },
    {
        "code_station": "01097000",
        "libelle_station": "LA TERNOISE \u00c0 AUCHY LES HESDIN (62)",
        "localisation": "PONT DU CD 123",
        "uri_station": "https:\/\/id.eaufrance.fr\/StationMesureEauxSurface\/01097000",
        "longitude": 2.1026201,
        "latitude": 50.397567967,
        "code_commune": "62050",
        "libelle_commune": "Auchy-l\u00e8s-Hesdin",
        "code_cours_eau": "E5400650",
        "libelle_cours_eau": "Ternoise",
        "uri_cours_eau": "https:\/\/id.eaufrance.fr\/CoursEau_Carthage2017\/E5400650",
        "date_mesure_temp": "2011-11-01",
        "heure_mesure_temp": "00:00:00",
        "resultat": 11.419
    },
    {
        "code_station": "01097000",
        "libelle_station": "LA TERNOISE \u00c0 AUCHY LES HESDIN (62)",
        "localisation": "PONT DU CD 123",
        "uri_station": "https:\/\/id.eaufrance.fr\/StationMesureEauxSurface\/01097000",
        "longitude": 2.1026201,
        "latitude": 50.397567967,
        "code_commune": "62050",
        "libelle_commune": "Auchy-l\u00e8s-Hesdin",
        "code_cours_eau": "E5400650",
        "libelle_cours_eau": "Ternoise",
        "uri_cours_eau": "https:\/\/id.eaufrance.fr\/CoursEau_Carthage2017\/E5400650",
        "date_mesure_temp": "2011-12-01",
        "heure_mesure_temp": "00:00:00",
        "resultat": 8.866
    },
    {
        "code_station": "01097000",
        "libelle_station": "LA TERNOISE \u00c0 AUCHY LES HESDIN (62)",
        "localisation": "PONT DU CD 123",
        "uri_station": "https:\/\/id.eaufrance.fr\/StationMesureEauxSurface\/01097000",
        "longitude": 2.1026201,
        "latitude": 50.397567967,
        "code_commune": "62050",
        "libelle_commune": "Auchy-l\u00e8s-Hesdin",
        "code_cours_eau": "E5400650",
        "libelle_cours_eau": "Ternoise",
        "uri_cours_eau": "https:\/\/id.eaufrance.fr\/CoursEau_Carthage2017\/E5400650",
        "date_mesure_temp": "2012-01-01",
        "heure_mesure_temp": "00:00:00",
        "resultat": 10.1
    },
    {
        "code_station": "01097000",
        "libelle_station": "LA TERNOISE \u00c0 AUCHY LES HESDIN (62)",
        "localisation": "PONT DU CD 123",
        "uri_station": "https:\/\/id.eaufrance.fr\/StationMesureEauxSurface\/01097000",
        "longitude": 2.1026201,
        "latitude": 50.397567967,
        "code_commune": "62050",
        "libelle_commune": "Auchy-l\u00e8s-Hesdin",
        "code_cours_eau": "E5400650",
        "libelle_cours_eau": "Ternoise",
        "uri_cours_eau": "https:\/\/id.eaufrance.fr\/CoursEau_Carthage2017\/E5400650",
        "date_mesure_temp": "2012-02-01",
        "heure_mesure_temp": "00:00:00",
        "resultat": 8.195
    },
    {
        "code_station": "01097000",
        "libelle_station": "LA TERNOISE \u00c0 AUCHY LES HESDIN (62)",
        "localisation": "PONT DU CD 123",
        "uri_station": "https:\/\/id.eaufrance.fr\/StationMesureEauxSurface\/01097000",
        "longitude": 2.1026201,
        "latitude": 50.397567967,
        "code_commune": "62050",
        "libelle_commune": "Auchy-l\u00e8s-Hesdin",
        "code_cours_eau": "E5400650",
        "libelle_cours_eau": "Ternoise",
        "uri_cours_eau": "https:\/\/id.eaufrance.fr\/CoursEau_Carthage2017\/E5400650",
        "date_mesure_temp": "2012-03-01",
        "heure_mesure_temp": "00:00:00",
        "resultat": 10.173
    },
    {
        "code_station": "01097000",
        "libelle_station": "LA TERNOISE \u00c0 AUCHY LES HESDIN (62)",
        "localisation": "PONT DU CD 123",
        "uri_station": "https:\/\/id.eaufrance.fr\/StationMesureEauxSurface\/01097000",
        "longitude": 2.1026201,
        "latitude": 50.397567967,
        "code_commune": "62050",
        "libelle_commune": "Auchy-l\u00e8s-Hesdin",
        "code_cours_eau": "E5400650",
        "libelle_cours_eau": "Ternoise",
        "uri_cours_eau": "https:\/\/id.eaufrance.fr\/CoursEau_Carthage2017\/E5400650",
        "date_mesure_temp": "2012-04-01",
        "heure_mesure_temp": "00:00:00",
        "resultat": 10.516
    },
    {
        "code_station": "01097000",
        "libelle_station": "LA TERNOISE \u00c0 AUCHY LES HESDIN (62)",
        "localisation": "PONT DU CD 123",
        "uri_station": "https:\/\/id.eaufrance.fr\/StationMesureEauxSurface\/01097000",
        "longitude": 2.1026201,
        "latitude": 50.397567967,
        "code_commune": "62050",
        "libelle_commune": "Auchy-l\u00e8s-Hesdin",
        "code_cours_eau": "E5400650",
        "libelle_cours_eau": "Ternoise",
        "uri_cours_eau": "https:\/\/id.eaufrance.fr\/CoursEau_Carthage2017\/E5400650",
        "date_mesure_temp": "2012-05-01",
        "heure_mesure_temp": "00:00:00",
        "resultat": 10.858
    },
    {
        "code_station": "01097000",
        "libelle_station": "LA TERNOISE \u00c0 AUCHY LES HESDIN (62)",
        "localisation": "PONT DU CD 123",
        "uri_station": "https:\/\/id.eaufrance.fr\/StationMesureEauxSurface\/01097000",
        "longitude": 2.1026201,
        "latitude": 50.397567967,
        "code_commune": "62050",
        "libelle_commune": "Auchy-l\u00e8s-Hesdin",
        "code_cours_eau": "E5400650",
        "libelle_cours_eau": "Ternoise",
        "uri_cours_eau": "https:\/\/id.eaufrance.fr\/CoursEau_Carthage2017\/E5400650",
        "date_mesure_temp": "2012-06-01",
        "heure_mesure_temp": "00:00:00",
        "resultat": 12.92
    },
    {
        "code_station": "01097000",
        "libelle_station": "LA TERNOISE \u00c0 AUCHY LES HESDIN (62)",
        "localisation": "PONT DU CD 123",
        "uri_station": "https:\/\/id.eaufrance.fr\/StationMesureEauxSurface\/01097000",
        "longitude": 2.1026201,
        "latitude": 50.397567967,
        "code_commune": "62050",
        "libelle_commune": "Auchy-l\u00e8s-Hesdin",
        "code_cours_eau": "E5400650",
        "libelle_cours_eau": "Ternoise",
        "uri_cours_eau": "https:\/\/id.eaufrance.fr\/CoursEau_Carthage2017\/E5400650",
        "date_mesure_temp": "2012-07-01",
        "heure_mesure_temp": "00:00:00",
        "resultat": 13.401
    },
    {
        "code_station": "01097000",
        "libelle_station": "LA TERNOISE \u00c0 AUCHY LES HESDIN (62)",
        "localisation": "PONT DU CD 123",
        "uri_station": "https:\/\/id.eaufrance.fr\/StationMesureEauxSurface\/01097000",
        "longitude": 2.1026201,
        "latitude": 50.397567967,
        "code_commune": "62050",
        "libelle_commune": "Auchy-l\u00e8s-Hesdin",
        "code_cours_eau": "E5400650",
        "libelle_cours_eau": "Ternoise",
        "uri_cours_eau": "https:\/\/id.eaufrance.fr\/CoursEau_Carthage2017\/E5400650",
        "date_mesure_temp": "2012-08-01",
        "heure_mesure_temp": "00:00:00",
        "resultat": 12.654
    },
    {
        "code_station": "01097000",
        "libelle_station": "LA TERNOISE \u00c0 AUCHY LES HESDIN (62)",
        "localisation": "PONT DU CD 123",
        "uri_station": "https:\/\/id.eaufrance.fr\/StationMesureEauxSurface\/01097000",
        "longitude": 2.1026201,
        "latitude": 50.397567967,
        "code_commune": "62050",
        "libelle_commune": "Auchy-l\u00e8s-Hesdin",
        "code_cours_eau": "E5400650",
        "libelle_cours_eau": "Ternoise",
        "uri_cours_eau": "https:\/\/id.eaufrance.fr\/CoursEau_Carthage2017\/E5400650",
        "date_mesure_temp": "2012-09-01",
        "heure_mesure_temp": "00:00:00",
        "resultat": 12.364
    },
    {
        "code_station": "01097000",
        "libelle_station": "LA TERNOISE \u00c0 AUCHY LES HESDIN (62)",
        "localisation": "PONT DU CD 123",
        "uri_station": "https:\/\/id.eaufrance.fr\/StationMesureEauxSurface\/01097000",
        "longitude": 2.1026201,
        "latitude": 50.397567967,
        "code_commune": "62050",
        "libelle_commune": "Auchy-l\u00e8s-Hesdin",
        "code_cours_eau": "E5400650",
        "libelle_cours_eau": "Ternoise",
        "uri_cours_eau": "https:\/\/id.eaufrance.fr\/CoursEau_Carthage2017\/E5400650",
        "date_mesure_temp": "2012-10-01",
        "heure_mesure_temp": "00:00:00",
        "resultat": 11.078
    },
    {
        "code_station": "01097000",
        "libelle_station": "LA TERNOISE \u00c0 AUCHY LES HESDIN (62)",
        "localisation": "PONT DU CD 123",
        "uri_station": "https:\/\/id.eaufrance.fr\/StationMesureEauxSurface\/01097000",
        "longitude": 2.1026201,
        "latitude": 50.397567967,
        "code_commune": "62050",
        "libelle_commune": "Auchy-l\u00e8s-Hesdin",
        "code_cours_eau": "E5400650",
        "libelle_cours_eau": "Ternoise",
        "uri_cours_eau": "https:\/\/id.eaufrance.fr\/CoursEau_Carthage2017\/E5400650",
        "date_mesure_temp": "2012-11-01",
        "heure_mesure_temp": "00:00:00",
        "resultat": 10.001
    },
    {
        "code_station": "01097000",
        "libelle_station": "LA TERNOISE \u00c0 AUCHY LES HESDIN (62)",
        "localisation": "PONT DU CD 123",
        "uri_station": "https:\/\/id.eaufrance.fr\/StationMesureEauxSurface\/01097000",
        "longitude": 2.1026201,
        "latitude": 50.397567967,
        "code_commune": "62050",
        "libelle_commune": "Auchy-l\u00e8s-Hesdin",
        "code_cours_eau": "E5400650",
        "libelle_cours_eau": "Ternoise",
        "uri_cours_eau": "https:\/\/id.eaufrance.fr\/CoursEau_Carthage2017\/E5400650",
        "date_mesure_temp": "2012-12-01",
        "heure_mesure_temp": "00:00:00",
        "resultat": 8.817
    },
    {
        "code_station": "01097000",
        "libelle_station": "LA TERNOISE \u00c0 AUCHY LES HESDIN (62)",
        "localisation": "PONT DU CD 123",
        "uri_station": "https:\/\/id.eaufrance.fr\/StationMesureEauxSurface\/01097000",
        "longitude": 2.1026201,
        "latitude": 50.397567967,
        "code_commune": "62050",
        "libelle_commune": "Auchy-l\u00e8s-Hesdin",
        "code_cours_eau": "E5400650",
        "libelle_cours_eau": "Ternoise",
        "uri_cours_eau": "https:\/\/id.eaufrance.fr\/CoursEau_Carthage2017\/E5400650",
        "date_mesure_temp": "2013-01-10",
        "heure_mesure_temp": "18:00:00",
        "resultat": 8.444
    },
    {
        "code_station": "01097000",
        "libelle_station": "LA TERNOISE \u00c0 AUCHY LES HESDIN (62)",
        "localisation": "PONT DU CD 123",
        "uri_station": "https:\/\/id.eaufrance.fr\/StationMesureEauxSurface\/01097000",
        "longitude": 2.1026201,
        "latitude": 50.397567967,
        "code_commune": "62050",
        "libelle_commune": "Auchy-l\u00e8s-Hesdin",
        "code_cours_eau": "E5400650",
        "libelle_cours_eau": "Ternoise",
        "uri_cours_eau": "https:\/\/id.eaufrance.fr\/CoursEau_Carthage2017\/E5400650",
        "date_mesure_temp": "2013-02-01",
        "heure_mesure_temp": "00:00:00",
        "resultat": 9.188
    },
    {
        "code_station": "01097000",
        "libelle_station": "LA TERNOISE \u00c0 AUCHY LES HESDIN (62)",
        "localisation": "PONT DU CD 123",
        "uri_station": "https:\/\/id.eaufrance.fr\/StationMesureEauxSurface\/01097000",
        "longitude": 2.1026201,
        "latitude": 50.397567967,
        "code_commune": "62050",
        "libelle_commune": "Auchy-l\u00e8s-Hesdin",
        "code_cours_eau": "E5400650",
        "libelle_cours_eau": "Ternoise",
        "uri_cours_eau": "https:\/\/id.eaufrance.fr\/CoursEau_Carthage2017\/E5400650",
        "date_mesure_temp": "2013-03-01",
        "heure_mesure_temp": "00:00:00",
        "resultat": 10.075
    },
    {
        "code_station": "01097000",
        "libelle_station": "LA TERNOISE \u00c0 AUCHY LES HESDIN (62)",
        "localisation": "PONT DU CD 123",
        "uri_station": "https:\/\/id.eaufrance.fr\/StationMesureEauxSurface\/01097000",
        "longitude": 2.1026201,
        "latitude": 50.397567967,
        "code_commune": "62050",
        "libelle_commune": "Auchy-l\u00e8s-Hesdin",
        "code_cours_eau": "E5400650",
        "libelle_cours_eau": "Ternoise",
        "uri_cours_eau": "https:\/\/id.eaufrance.fr\/CoursEau_Carthage2017\/E5400650",
        "date_mesure_temp": "2013-04-01",
        "heure_mesure_temp": "00:00:00",
        "resultat": 8.668
    },
    {
        "code_station": "01097000",
        "libelle_station": "LA TERNOISE \u00c0 AUCHY LES HESDIN (62)",
        "localisation": "PONT DU CD 123",
        "uri_station": "https:\/\/id.eaufrance.fr\/StationMesureEauxSurface\/01097000",
        "longitude": 2.1026201,
        "latitude": 50.397567967,
        "code_commune": "62050",
        "libelle_commune": "Auchy-l\u00e8s-Hesdin",
        "code_cours_eau": "E5400650",
        "libelle_cours_eau": "Ternoise",
        "uri_cours_eau": "https:\/\/id.eaufrance.fr\/CoursEau_Carthage2017\/E5400650",
        "date_mesure_temp": "2013-05-01",
        "heure_mesure_temp": "00:00:00",
        "resultat": 9.089
    },
    {
        "code_station": "01097000",
        "libelle_station": "LA TERNOISE \u00c0 AUCHY LES HESDIN (62)",
        "localisation": "PONT DU CD 123",
        "uri_station": "https:\/\/id.eaufrance.fr\/StationMesureEauxSurface\/01097000",
        "longitude": 2.1026201,
        "latitude": 50.397567967,
        "code_commune": "62050",
        "libelle_commune": "Auchy-l\u00e8s-Hesdin",
        "code_cours_eau": "E5400650",
        "libelle_cours_eau": "Ternoise",
        "uri_cours_eau": "https:\/\/id.eaufrance.fr\/CoursEau_Carthage2017\/E5400650",
        "date_mesure_temp": "2013-06-01",
        "heure_mesure_temp": "00:00:00",
        "resultat": 11.759
    },
    {
        "code_station": "01097000",
        "libelle_station": "LA TERNOISE \u00c0 AUCHY LES HESDIN (62)",
        "localisation": "PONT DU CD 123",
        "uri_station": "https:\/\/id.eaufrance.fr\/StationMesureEauxSurface\/01097000",
        "longitude": 2.1026201,
        "latitude": 50.397567967,
        "code_commune": "62050",
        "libelle_commune": "Auchy-l\u00e8s-Hesdin",
        "code_cours_eau": "E5400650",
        "libelle_cours_eau": "Ternoise",
        "uri_cours_eau": "https:\/\/id.eaufrance.fr\/CoursEau_Carthage2017\/E5400650",
        "date_mesure_temp": "2013-07-01",
        "heure_mesure_temp": "00:00:00",
        "resultat": 12.147
    },
    {
        "code_station": "01097000",
        "libelle_station": "LA TERNOISE \u00c0 AUCHY LES HESDIN (62)",
        "localisation": "PONT DU CD 123",
        "uri_station": "https:\/\/id.eaufrance.fr\/StationMesureEauxSurface\/01097000",
        "longitude": 2.1026201,
        "latitude": 50.397567967,
        "code_commune": "62050",
        "libelle_commune": "Auchy-l\u00e8s-Hesdin",
        "code_cours_eau": "E5400650",
        "libelle_cours_eau": "Ternoise",
        "uri_cours_eau": "https:\/\/id.eaufrance.fr\/CoursEau_Carthage2017\/E5400650",
        "date_mesure_temp": "2013-08-01",
        "heure_mesure_temp": "00:00:00",
        "resultat": 12.292
    },
    {
        "code_station": "01097000",
        "libelle_station": "LA TERNOISE \u00c0 AUCHY LES HESDIN (62)",
        "localisation": "PONT DU CD 123",
        "uri_station": "https:\/\/id.eaufrance.fr\/StationMesureEauxSurface\/01097000",
        "longitude": 2.1026201,
        "latitude": 50.397567967,
        "code_commune": "62050",
        "libelle_commune": "Auchy-l\u00e8s-Hesdin",
        "code_cours_eau": "E5400650",
        "libelle_cours_eau": "Ternoise",
        "uri_cours_eau": "https:\/\/id.eaufrance.fr\/CoursEau_Carthage2017\/E5400650",
        "date_mesure_temp": "2014-10-09",
        "heure_mesure_temp": "17:00:00",
        "resultat": 12.2679996490479
    },
    {
        "code_station": "01097000",
        "libelle_station": "LA TERNOISE \u00c0 AUCHY LES HESDIN (62)",
        "localisation": "PONT DU CD 123",
        "uri_station": "https:\/\/id.eaufrance.fr\/StationMesureEauxSurface\/01097000",
        "longitude": 2.1026201,
        "latitude": 50.397567967,
        "code_commune": "62050",
        "libelle_commune": "Auchy-l\u00e8s-Hesdin",
        "code_cours_eau": "E5400650",
        "libelle_cours_eau": "Ternoise",
        "uri_cours_eau": "https:\/\/id.eaufrance.fr\/CoursEau_Carthage2017\/E5400650",
        "date_mesure_temp": "2014-11-01",
        "heure_mesure_temp": "00:00:00",
        "resultat": 11.418999671936
    },
    {
        "code_station": "01097000",
        "libelle_station": "LA TERNOISE \u00c0 AUCHY LES HESDIN (62)",
        "localisation": "PONT DU CD 123",
        "uri_station": "https:\/\/id.eaufrance.fr\/StationMesureEauxSurface\/01097000",
        "longitude": 2.1026201,
        "latitude": 50.397567967,
        "code_commune": "62050",
        "libelle_commune": "Auchy-l\u00e8s-Hesdin",
        "code_cours_eau": "E5400650",
        "libelle_cours_eau": "Ternoise",
        "uri_cours_eau": "https:\/\/id.eaufrance.fr\/CoursEau_Carthage2017\/E5400650",
        "date_mesure_temp": "2014-12-01",
        "heure_mesure_temp": "00:00:00",
        "resultat": 9.4350004196167
    },
    {
        "code_station": "01097000",
        "libelle_station": "LA TERNOISE \u00c0 AUCHY LES HESDIN (62)",
        "localisation": "PONT DU CD 123",
        "uri_station": "https:\/\/id.eaufrance.fr\/StationMesureEauxSurface\/01097000",
        "longitude": 2.1026201,
        "latitude": 50.397567967,
        "code_commune": "62050",
        "libelle_commune": "Auchy-l\u00e8s-Hesdin",
        "code_cours_eau": "E5400650",
        "libelle_cours_eau": "Ternoise",
        "uri_cours_eau": "https:\/\/id.eaufrance.fr\/CoursEau_Carthage2017\/E5400650",
        "date_mesure_temp": "2015-01-01",
        "heure_mesure_temp": "00:00:00",
        "resultat": 8.24499988555908
    },
    {
        "code_station": "01097000",
        "libelle_station": "LA TERNOISE \u00c0 AUCHY LES HESDIN (62)",
        "localisation": "PONT DU CD 123",
        "uri_station": "https:\/\/id.eaufrance.fr\/StationMesureEauxSurface\/01097000",
        "longitude": 2.1026201,
        "latitude": 50.397567967,
        "code_commune": "62050",
        "libelle_commune": "Auchy-l\u00e8s-Hesdin",
        "code_cours_eau": "E5400650",
        "libelle_cours_eau": "Ternoise",
        "uri_cours_eau": "https:\/\/id.eaufrance.fr\/CoursEau_Carthage2017\/E5400650",
        "date_mesure_temp": "2015-02-01",
        "heure_mesure_temp": "00:00:00",
        "resultat": 8.3439998626709
    },
    {
        "code_station": "01097000",
        "libelle_station": "LA TERNOISE \u00c0 AUCHY LES HESDIN (62)",
        "localisation": "PONT DU CD 123",
        "uri_station": "https:\/\/id.eaufrance.fr\/StationMesureEauxSurface\/01097000",
        "longitude": 2.1026201,
        "latitude": 50.397567967,
        "code_commune": "62050",
        "libelle_commune": "Auchy-l\u00e8s-Hesdin",
        "code_cours_eau": "E5400650",
        "libelle_cours_eau": "Ternoise",
        "uri_cours_eau": "https:\/\/id.eaufrance.fr\/CoursEau_Carthage2017\/E5400650",
        "date_mesure_temp": "2015-03-01",
        "heure_mesure_temp": "00:00:00",
        "resultat": 9.3120002746582
    },
    {
        "code_station": "01097000",
        "libelle_station": "LA TERNOISE \u00c0 AUCHY LES HESDIN (62)",
        "localisation": "PONT DU CD 123",
        "uri_station": "https:\/\/id.eaufrance.fr\/StationMesureEauxSurface\/01097000",
        "longitude": 2.1026201,
        "latitude": 50.397567967,
        "code_commune": "62050",
        "libelle_commune": "Auchy-l\u00e8s-Hesdin",
        "code_cours_eau": "E5400650",
        "libelle_cours_eau": "Ternoise",
        "uri_cours_eau": "https:\/\/id.eaufrance.fr\/CoursEau_Carthage2017\/E5400650",
        "date_mesure_temp": "2015-04-01",
        "heure_mesure_temp": "00:00:00",
        "resultat": 10.7360000610352
    },
    {
        "code_station": "01097000",
        "libelle_station": "LA TERNOISE \u00c0 AUCHY LES HESDIN (62)",
        "localisation": "PONT DU CD 123",
        "uri_station": "https:\/\/id.eaufrance.fr\/StationMesureEauxSurface\/01097000",
        "longitude": 2.1026201,
        "latitude": 50.397567967,
        "code_commune": "62050",
        "libelle_commune": "Auchy-l\u00e8s-Hesdin",
        "code_cours_eau": "E5400650",
        "libelle_cours_eau": "Ternoise",
        "uri_cours_eau": "https:\/\/id.eaufrance.fr\/CoursEau_Carthage2017\/E5400650",
        "date_mesure_temp": "2015-05-01",
        "heure_mesure_temp": "00:00:00",
        "resultat": 11.3940000534058
    },
    {
        "code_station": "01097000",
        "libelle_station": "LA TERNOISE \u00c0 AUCHY LES HESDIN (62)",
        "localisation": "PONT DU CD 123",
        "uri_station": "https:\/\/id.eaufrance.fr\/StationMesureEauxSurface\/01097000",
        "longitude": 2.1026201,
        "latitude": 50.397567967,
        "code_commune": "62050",
        "libelle_commune": "Auchy-l\u00e8s-Hesdin",
        "code_cours_eau": "E5400650",
        "libelle_cours_eau": "Ternoise",
        "uri_cours_eau": "https:\/\/id.eaufrance.fr\/CoursEau_Carthage2017\/E5400650",
        "date_mesure_temp": "2015-06-01",
        "heure_mesure_temp": "00:00:00",
        "resultat": 11.539999961853
    },
    {
        "code_station": "01097000",
        "libelle_station": "LA TERNOISE \u00c0 AUCHY LES HESDIN (62)",
        "localisation": "PONT DU CD 123",
        "uri_station": "https:\/\/id.eaufrance.fr\/StationMesureEauxSurface\/01097000",
        "longitude": 2.1026201,
        "latitude": 50.397567967,
        "code_commune": "62050",
        "libelle_commune": "Auchy-l\u00e8s-Hesdin",
        "code_cours_eau": "E5400650",
        "libelle_cours_eau": "Ternoise",
        "uri_cours_eau": "https:\/\/id.eaufrance.fr\/CoursEau_Carthage2017\/E5400650",
        "date_mesure_temp": "2015-07-01",
        "heure_mesure_temp": "00:00:00",
        "resultat": 11.3459997177124
    },
    {
        "code_station": "01097000",
        "libelle_station": "LA TERNOISE \u00c0 AUCHY LES HESDIN (62)",
        "localisation": "PONT DU CD 123",
        "uri_station": "https:\/\/id.eaufrance.fr\/StationMesureEauxSurface\/01097000",
        "longitude": 2.1026201,
        "latitude": 50.397567967,
        "code_commune": "62050",
        "libelle_commune": "Auchy-l\u00e8s-Hesdin",
        "code_cours_eau": "E5400650",
        "libelle_cours_eau": "Ternoise",
        "uri_cours_eau": "https:\/\/id.eaufrance.fr\/CoursEau_Carthage2017\/E5400650",
        "date_mesure_temp": "2015-08-01",
        "heure_mesure_temp": "00:00:00",
        "resultat": 10.7119998931885
    },
    {
        "code_station": "01097000",
        "libelle_station": "LA TERNOISE \u00c0 AUCHY LES HESDIN (62)",
        "localisation": "PONT DU CD 123",
        "uri_station": "https:\/\/id.eaufrance.fr\/StationMesureEauxSurface\/01097000",
        "longitude": 2.1026201,
        "latitude": 50.397567967,
        "code_commune": "62050",
        "libelle_commune": "Auchy-l\u00e8s-Hesdin",
        "code_cours_eau": "E5400650",
        "libelle_cours_eau": "Ternoise",
        "uri_cours_eau": "https:\/\/id.eaufrance.fr\/CoursEau_Carthage2017\/E5400650",
        "date_mesure_temp": "2015-09-01",
        "heure_mesure_temp": "00:00:00",
        "resultat": 6.63600015640259
    },
    {
        "code_station": "01097000",
        "libelle_station": "LA TERNOISE \u00c0 AUCHY LES HESDIN (62)",
        "localisation": "PONT DU CD 123",
        "uri_station": "https:\/\/id.eaufrance.fr\/StationMesureEauxSurface\/01097000",
        "longitude": 2.1026201,
        "latitude": 50.397567967,
        "code_commune": "62050",
        "libelle_commune": "Auchy-l\u00e8s-Hesdin",
        "code_cours_eau": "E5400650",
        "libelle_cours_eau": "Ternoise",
        "uri_cours_eau": "https:\/\/id.eaufrance.fr\/CoursEau_Carthage2017\/E5400650",
        "date_mesure_temp": "2015-10-01",
        "heure_mesure_temp": "00:00:00",
        "resultat": 9.1879997253418
    },
    {
        "code_station": "01097000",
        "libelle_station": "LA TERNOISE \u00c0 AUCHY LES HESDIN (62)",
        "localisation": "PONT DU CD 123",
        "uri_station": "https:\/\/id.eaufrance.fr\/StationMesureEauxSurface\/01097000",
        "longitude": 2.1026201,
        "latitude": 50.397567967,
        "code_commune": "62050",
        "libelle_commune": "Auchy-l\u00e8s-Hesdin",
        "code_cours_eau": "E5400650",
        "libelle_cours_eau": "Ternoise",
        "uri_cours_eau": "https:\/\/id.eaufrance.fr\/CoursEau_Carthage2017\/E5400650",
        "date_mesure_temp": "2015-11-01",
        "heure_mesure_temp": "00:00:00",
        "resultat": 9.06400012969971
    },
    {
        "code_station": "01097000",
        "libelle_station": "LA TERNOISE \u00c0 AUCHY LES HESDIN (62)",
        "localisation": "PONT DU CD 123",
        "uri_station": "https:\/\/id.eaufrance.fr\/StationMesureEauxSurface\/01097000",
        "longitude": 2.1026201,
        "latitude": 50.397567967,
        "code_commune": "62050",
        "libelle_commune": "Auchy-l\u00e8s-Hesdin",
        "code_cours_eau": "E5400650",
        "libelle_cours_eau": "Ternoise",
        "uri_cours_eau": "https:\/\/id.eaufrance.fr\/CoursEau_Carthage2017\/E5400650",
        "date_mesure_temp": "2015-12-01",
        "heure_mesure_temp": "00:00:00",
        "resultat": 10.1239995956421
    },
    {
        "code_station": "01097000",
        "libelle_station": "LA TERNOISE \u00c0 AUCHY LES HESDIN (62)",
        "localisation": "PONT DU CD 123",
        "uri_station": "https:\/\/id.eaufrance.fr\/StationMesureEauxSurface\/01097000",
        "longitude": 2.1026201,
        "latitude": 50.397567967,
        "code_commune": "62050",
        "libelle_commune": "Auchy-l\u00e8s-Hesdin",
        "code_cours_eau": "E5400650",
        "libelle_cours_eau": "Ternoise",
        "uri_cours_eau": "https:\/\/id.eaufrance.fr\/CoursEau_Carthage2017\/E5400650",
        "date_mesure_temp": "2016-01-01",
        "heure_mesure_temp": "00:00:00",
        "resultat": 11.2729997634888
    },
    {
        "code_station": "01097000",
        "libelle_station": "LA TERNOISE \u00c0 AUCHY LES HESDIN (62)",
        "localisation": "PONT DU CD 123",
        "uri_station": "https:\/\/id.eaufrance.fr\/StationMesureEauxSurface\/01097000",
        "longitude": 2.1026201,
        "latitude": 50.397567967,
        "code_commune": "62050",
        "libelle_commune": "Auchy-l\u00e8s-Hesdin",
        "code_cours_eau": "E5400650",
        "libelle_cours_eau": "Ternoise",
        "uri_cours_eau": "https:\/\/id.eaufrance.fr\/CoursEau_Carthage2017\/E5400650",
        "date_mesure_temp": "2016-02-01",
        "heure_mesure_temp": "00:00:00",
        "resultat": 11.710000038147
    },
    {
        "code_station": "01097000",
        "libelle_station": "LA TERNOISE \u00c0 AUCHY LES HESDIN (62)",
        "localisation": "PONT DU CD 123",
        "uri_station": "https:\/\/id.eaufrance.fr\/StationMesureEauxSurface\/01097000",
        "longitude": 2.1026201,
        "latitude": 50.397567967,
        "code_commune": "62050",
        "libelle_commune": "Auchy-l\u00e8s-Hesdin",
        "code_cours_eau": "E5400650",
        "libelle_cours_eau": "Ternoise",
        "uri_cours_eau": "https:\/\/id.eaufrance.fr\/CoursEau_Carthage2017\/E5400650",
        "date_mesure_temp": "2018-06-11",
        "heure_mesure_temp": "16:01:07",
        "resultat": 13.3290004730225
    },
    {
        "code_station": "01097000",
        "libelle_station": "LA TERNOISE \u00c0 AUCHY LES HESDIN (62)",
        "localisation": "PONT DU CD 123",
        "uri_station": "https:\/\/id.eaufrance.fr\/StationMesureEauxSurface\/01097000",
        "longitude": 2.1026201,
        "latitude": 50.397567967,
        "code_commune": "62050",
        "libelle_commune": "Auchy-l\u00e8s-Hesdin",
        "code_cours_eau": "E5400650",
        "libelle_cours_eau": "Ternoise",
        "uri_cours_eau": "https:\/\/id.eaufrance.fr\/CoursEau_Carthage2017\/E5400650",
        "date_mesure_temp": "2018-07-01",
        "heure_mesure_temp": "00:01:07",
        "resultat": 13.9060001373291
    },
    {
        "code_station": "01097000",
        "libelle_station": "LA TERNOISE \u00c0 AUCHY LES HESDIN (62)",
        "localisation": "PONT DU CD 123",
        "uri_station": "https:\/\/id.eaufrance.fr\/StationMesureEauxSurface\/01097000",
        "longitude": 2.1026201,
        "latitude": 50.397567967,
        "code_commune": "62050",
        "libelle_commune": "Auchy-l\u00e8s-Hesdin",
        "code_cours_eau": "E5400650",
        "libelle_cours_eau": "Ternoise",
        "uri_cours_eau": "https:\/\/id.eaufrance.fr\/CoursEau_Carthage2017\/E5400650",
        "date_mesure_temp": "2018-08-01",
        "heure_mesure_temp": "00:01:07",
        "resultat": 13.4969997406006
    },
    {
        "code_station": "01097000",
        "libelle_station": "LA TERNOISE \u00c0 AUCHY LES HESDIN (62)",
        "localisation": "PONT DU CD 123",
        "uri_station": "https:\/\/id.eaufrance.fr\/StationMesureEauxSurface\/01097000",
        "longitude": 2.1026201,
        "latitude": 50.397567967,
        "code_commune": "62050",
        "libelle_commune": "Auchy-l\u00e8s-Hesdin",
        "code_cours_eau": "E5400650",
        "libelle_cours_eau": "Ternoise",
        "uri_cours_eau": "https:\/\/id.eaufrance.fr\/CoursEau_Carthage2017\/E5400650",
        "date_mesure_temp": "2018-09-01",
        "heure_mesure_temp": "00:01:07",
        "resultat": 12.2679996490479
    },
    {
        "code_station": "01097000",
        "libelle_station": "LA TERNOISE \u00c0 AUCHY LES HESDIN (62)",
        "localisation": "PONT DU CD 123",
        "uri_station": "https:\/\/id.eaufrance.fr\/StationMesureEauxSurface\/01097000",
        "longitude": 2.1026201,
        "latitude": 50.397567967,
        "code_commune": "62050",
        "libelle_commune": "Auchy-l\u00e8s-Hesdin",
        "code_cours_eau": "E5400650",
        "libelle_cours_eau": "Ternoise",
        "uri_cours_eau": "https:\/\/id.eaufrance.fr\/CoursEau_Carthage2017\/E5400650",
        "date_mesure_temp": "2018-10-01",
        "heure_mesure_temp": "00:01:07",
        "resultat": 10.9799995422363
    },
    {
        "code_station": "01097000",
        "libelle_station": "LA TERNOISE \u00c0 AUCHY LES HESDIN (62)",
        "localisation": "PONT DU CD 123",
        "uri_station": "https:\/\/id.eaufrance.fr\/StationMesureEauxSurface\/01097000",
        "longitude": 2.1026201,
        "latitude": 50.397567967,
        "code_commune": "62050",
        "libelle_commune": "Auchy-l\u00e8s-Hesdin",
        "code_cours_eau": "E5400650",
        "libelle_cours_eau": "Ternoise",
        "uri_cours_eau": "https:\/\/id.eaufrance.fr\/CoursEau_Carthage2017\/E5400650",
        "date_mesure_temp": "2018-11-01",
        "heure_mesure_temp": "00:01:07",
        "resultat": 10.1979999542236
    },
    {
        "code_station": "01097000",
        "libelle_station": "LA TERNOISE \u00c0 AUCHY LES HESDIN (62)",
        "localisation": "PONT DU CD 123",
        "uri_station": "https:\/\/id.eaufrance.fr\/StationMesureEauxSurface\/01097000",
        "longitude": 2.1026201,
        "latitude": 50.397567967,
        "code_commune": "62050",
        "libelle_commune": "Auchy-l\u00e8s-Hesdin",
        "code_cours_eau": "E5400650",
        "libelle_cours_eau": "Ternoise",
        "uri_cours_eau": "https:\/\/id.eaufrance.fr\/CoursEau_Carthage2017\/E5400650",
        "date_mesure_temp": "2018-12-10",
        "heure_mesure_temp": "14:00:00",
        "resultat": 9.48499965667725
    },
    {
        "code_station": "01097000",
        "libelle_station": "LA TERNOISE \u00c0 AUCHY LES HESDIN (62)",
        "localisation": "PONT DU CD 123",
        "uri_station": "https:\/\/id.eaufrance.fr\/StationMesureEauxSurface\/01097000",
        "longitude": 2.1026201,
        "latitude": 50.397567967,
        "code_commune": "62050",
        "libelle_commune": "Auchy-l\u00e8s-Hesdin",
        "code_cours_eau": "E5400650",
        "libelle_cours_eau": "Ternoise",
        "uri_cours_eau": "https:\/\/id.eaufrance.fr\/CoursEau_Carthage2017\/E5400650",
        "date_mesure_temp": "2019-01-01",
        "heure_mesure_temp": "00:00:00",
        "resultat": 10.2469997406006
    },
    {
        "code_station": "01097000",
        "libelle_station": "LA TERNOISE \u00c0 AUCHY LES HESDIN (62)",
        "localisation": "PONT DU CD 123",
        "uri_station": "https:\/\/id.eaufrance.fr\/StationMesureEauxSurface\/01097000",
        "longitude": 2.1026201,
        "latitude": 50.397567967,
        "code_commune": "62050",
        "libelle_commune": "Auchy-l\u00e8s-Hesdin",
        "code_cours_eau": "E5400650",
        "libelle_cours_eau": "Ternoise",
        "uri_cours_eau": "https:\/\/id.eaufrance.fr\/CoursEau_Carthage2017\/E5400650",
        "date_mesure_temp": "2019-02-01",
        "heure_mesure_temp": "00:00:00",
        "resultat": 7.39300012588501
    },
    {
        "code_station": "01097000",
        "libelle_station": "LA TERNOISE \u00c0 AUCHY LES HESDIN (62)",
        "localisation": "PONT DU CD 123",
        "uri_station": "https:\/\/id.eaufrance.fr\/StationMesureEauxSurface\/01097000",
        "longitude": 2.1026201,
        "latitude": 50.397567967,
        "code_commune": "62050",
        "libelle_commune": "Auchy-l\u00e8s-Hesdin",
        "code_cours_eau": "E5400650",
        "libelle_cours_eau": "Ternoise",
        "uri_cours_eau": "https:\/\/id.eaufrance.fr\/CoursEau_Carthage2017\/E5400650",
        "date_mesure_temp": "2019-03-01",
        "heure_mesure_temp": "00:00:00",
        "resultat": 10.4180002212524
    },
    {
        "code_station": "01097000",
        "libelle_station": "LA TERNOISE \u00c0 AUCHY LES HESDIN (62)",
        "localisation": "PONT DU CD 123",
        "uri_station": "https:\/\/id.eaufrance.fr\/StationMesureEauxSurface\/01097000",
        "longitude": 2.1026201,
        "latitude": 50.397567967,
        "code_commune": "62050",
        "libelle_commune": "Auchy-l\u00e8s-Hesdin",
        "code_cours_eau": "E5400650",
        "libelle_cours_eau": "Ternoise",
        "uri_cours_eau": "https:\/\/id.eaufrance.fr\/CoursEau_Carthage2017\/E5400650",
        "date_mesure_temp": "2019-04-01",
        "heure_mesure_temp": "00:00:00",
        "resultat": 11.0290002822876
    },
    {
        "code_station": "01097000",
        "libelle_station": "LA TERNOISE \u00c0 AUCHY LES HESDIN (62)",
        "localisation": "PONT DU CD 123",
        "uri_station": "https:\/\/id.eaufrance.fr\/StationMesureEauxSurface\/01097000",
        "longitude": 2.1026201,
        "latitude": 50.397567967,
        "code_commune": "62050",
        "libelle_commune": "Auchy-l\u00e8s-Hesdin",
        "code_cours_eau": "E5400650",
        "libelle_cours_eau": "Ternoise",
        "uri_cours_eau": "https:\/\/id.eaufrance.fr\/CoursEau_Carthage2017\/E5400650",
        "date_mesure_temp": "2019-05-01",
        "heure_mesure_temp": "00:00:00",
        "resultat": 11.0530004501343
    },
    {
        "code_station": "01097000",
        "libelle_station": "LA TERNOISE \u00c0 AUCHY LES HESDIN (62)",
        "localisation": "PONT DU CD 123",
        "uri_station": "https:\/\/id.eaufrance.fr\/StationMesureEauxSurface\/01097000",
        "longitude": 2.1026201,
        "latitude": 50.397567967,
        "code_commune": "62050",
        "libelle_commune": "Auchy-l\u00e8s-Hesdin",
        "code_cours_eau": "E5400650",
        "libelle_cours_eau": "Ternoise",
        "uri_cours_eau": "https:\/\/id.eaufrance.fr\/CoursEau_Carthage2017\/E5400650",
        "date_mesure_temp": "2019-06-01",
        "heure_mesure_temp": "00:00:00",
        "resultat": 12.871000289917
    },
    {
        "code_station": "01097000",
        "libelle_station": "LA TERNOISE \u00c0 AUCHY LES HESDIN (62)",
        "localisation": "PONT DU CD 123",
        "uri_station": "https:\/\/id.eaufrance.fr\/StationMesureEauxSurface\/01097000",
        "longitude": 2.1026201,
        "latitude": 50.397567967,
        "code_commune": "62050",
        "libelle_commune": "Auchy-l\u00e8s-Hesdin",
        "code_cours_eau": "E5400650",
        "libelle_cours_eau": "Ternoise",
        "uri_cours_eau": "https:\/\/id.eaufrance.fr\/CoursEau_Carthage2017\/E5400650",
        "date_mesure_temp": "2019-07-01",
        "heure_mesure_temp": "00:00:00",
        "resultat": 13.7379999160767
    },
    {
        "code_station": "01097000",
        "libelle_station": "LA TERNOISE \u00c0 AUCHY LES HESDIN (62)",
        "localisation": "PONT DU CD 123",
        "uri_station": "https:\/\/id.eaufrance.fr\/StationMesureEauxSurface\/01097000",
        "longitude": 2.1026201,
        "latitude": 50.397567967,
        "code_commune": "62050",
        "libelle_commune": "Auchy-l\u00e8s-Hesdin",
        "code_cours_eau": "E5400650",
        "libelle_cours_eau": "Ternoise",
        "uri_cours_eau": "https:\/\/id.eaufrance.fr\/CoursEau_Carthage2017\/E5400650",
        "date_mesure_temp": "2019-08-01",
        "heure_mesure_temp": "00:00:00",
        "resultat": 13.6180000305176
    },
    {
        "code_station": "01097000",
        "libelle_station": "LA TERNOISE \u00c0 AUCHY LES HESDIN (62)",
        "localisation": "PONT DU CD 123",
        "uri_station": "https:\/\/id.eaufrance.fr\/StationMesureEauxSurface\/01097000",
        "longitude": 2.1026201,
        "latitude": 50.397567967,
        "code_commune": "62050",
        "libelle_commune": "Auchy-l\u00e8s-Hesdin",
        "code_cours_eau": "E5400650",
        "libelle_cours_eau": "Ternoise",
        "uri_cours_eau": "https:\/\/id.eaufrance.fr\/CoursEau_Carthage2017\/E5400650",
        "date_mesure_temp": "2019-09-01",
        "heure_mesure_temp": "00:00:00",
        "resultat": 13.1120004653931
    },
    {
        "code_station": "01097000",
        "libelle_station": "LA TERNOISE \u00c0 AUCHY LES HESDIN (62)",
        "localisation": "PONT DU CD 123",
        "uri_station": "https:\/\/id.eaufrance.fr\/StationMesureEauxSurface\/01097000",
        "longitude": 2.1026201,
        "latitude": 50.397567967,
        "code_commune": "62050",
        "libelle_commune": "Auchy-l\u00e8s-Hesdin",
        "code_cours_eau": "E5400650",
        "libelle_cours_eau": "Ternoise",
        "uri_cours_eau": "https:\/\/id.eaufrance.fr\/CoursEau_Carthage2017\/E5400650",
        "date_mesure_temp": "2019-10-01",
        "heure_mesure_temp": "00:00:00",
        "resultat": 12.3159999847412
    },
    {
        "code_station": "01097000",
        "libelle_station": "LA TERNOISE \u00c0 AUCHY LES HESDIN (62)",
        "localisation": "PONT DU CD 123",
        "uri_station": "https:\/\/id.eaufrance.fr\/StationMesureEauxSurface\/01097000",
        "longitude": 2.1026201,
        "latitude": 50.397567967,
        "code_commune": "62050",
        "libelle_commune": "Auchy-l\u00e8s-Hesdin",
        "code_cours_eau": "E5400650",
        "libelle_cours_eau": "Ternoise",
        "uri_cours_eau": "https:\/\/id.eaufrance.fr\/CoursEau_Carthage2017\/E5400650",
        "date_mesure_temp": "2019-11-01",
        "heure_mesure_temp": "00:00:00",
        "resultat": 10.1490001678467
    },
    {
        "code_station": "01097000",
        "libelle_station": "LA TERNOISE \u00c0 AUCHY LES HESDIN (62)",
        "localisation": "PONT DU CD 123",
        "uri_station": "https:\/\/id.eaufrance.fr\/StationMesureEauxSurface\/01097000",
        "longitude": 2.1026201,
        "latitude": 50.397567967,
        "code_commune": "62050",
        "libelle_commune": "Auchy-l\u00e8s-Hesdin",
        "code_cours_eau": "E5400650",
        "libelle_cours_eau": "Ternoise",
        "uri_cours_eau": "https:\/\/id.eaufrance.fr\/CoursEau_Carthage2017\/E5400650",
        "date_mesure_temp": "2019-12-01",
        "heure_mesure_temp": "00:00:00",
        "resultat": 8.86600017547607
    },
    {
        "code_station": "01097000",
        "libelle_station": "LA TERNOISE \u00c0 AUCHY LES HESDIN (62)",
        "localisation": "PONT DU CD 123",
        "uri_station": "https:\/\/id.eaufrance.fr\/StationMesureEauxSurface\/01097000",
        "longitude": 2.1026201,
        "latitude": 50.397567967,
        "code_commune": "62050",
        "libelle_commune": "Auchy-l\u00e8s-Hesdin",
        "code_cours_eau": "E5400650",
        "libelle_cours_eau": "Ternoise",
        "uri_cours_eau": "https:\/\/id.eaufrance.fr\/CoursEau_Carthage2017\/E5400650",
        "date_mesure_temp": "2020-01-01",
        "heure_mesure_temp": "00:00:00",
        "resultat": 8.94099998474121
    },
    {
        "code_station": "01097000",
        "libelle_station": "LA TERNOISE \u00c0 AUCHY LES HESDIN (62)",
        "localisation": "PONT DU CD 123",
        "uri_station": "https:\/\/id.eaufrance.fr\/StationMesureEauxSurface\/01097000",
        "longitude": 2.1026201,
        "latitude": 50.397567967,
        "code_commune": "62050",
        "libelle_commune": "Auchy-l\u00e8s-Hesdin",
        "code_cours_eau": "E5400650",
        "libelle_cours_eau": "Ternoise",
        "uri_cours_eau": "https:\/\/id.eaufrance.fr\/CoursEau_Carthage2017\/E5400650",
        "date_mesure_temp": "2020-02-01",
        "heure_mesure_temp": "00:00:00",
        "resultat": 10.7119998931885
    },
    {
        "code_station": "01097000",
        "libelle_station": "LA TERNOISE \u00c0 AUCHY LES HESDIN (62)",
        "localisation": "PONT DU CD 123",
        "uri_station": "https:\/\/id.eaufrance.fr\/StationMesureEauxSurface\/01097000",
        "longitude": 2.1026201,
        "latitude": 50.397567967,
        "code_commune": "62050",
        "libelle_commune": "Auchy-l\u00e8s-Hesdin",
        "code_cours_eau": "E5400650",
        "libelle_cours_eau": "Ternoise",
        "uri_cours_eau": "https:\/\/id.eaufrance.fr\/CoursEau_Carthage2017\/E5400650",
        "date_mesure_temp": "2020-03-01",
        "heure_mesure_temp": "00:00:00",
        "resultat": 9.1879997253418
    },
    {
        "code_station": "01097000",
        "libelle_station": "LA TERNOISE \u00c0 AUCHY LES HESDIN (62)",
        "localisation": "PONT DU CD 123",
        "uri_station": "https:\/\/id.eaufrance.fr\/StationMesureEauxSurface\/01097000",
        "longitude": 2.1026201,
        "latitude": 50.397567967,
        "code_commune": "62050",
        "libelle_commune": "Auchy-l\u00e8s-Hesdin",
        "code_cours_eau": "E5400650",
        "libelle_cours_eau": "Ternoise",
        "uri_cours_eau": "https:\/\/id.eaufrance.fr\/CoursEau_Carthage2017\/E5400650",
        "date_mesure_temp": "2020-04-01",
        "heure_mesure_temp": "00:00:00",
        "resultat": 10.0010004043579
    },
    {
        "code_station": "01097000",
        "libelle_station": "LA TERNOISE \u00c0 AUCHY LES HESDIN (62)",
        "localisation": "PONT DU CD 123",
        "uri_station": "https:\/\/id.eaufrance.fr\/StationMesureEauxSurface\/01097000",
        "longitude": 2.1026201,
        "latitude": 50.397567967,
        "code_commune": "62050",
        "libelle_commune": "Auchy-l\u00e8s-Hesdin",
        "code_cours_eau": "E5400650",
        "libelle_cours_eau": "Ternoise",
        "uri_cours_eau": "https:\/\/id.eaufrance.fr\/CoursEau_Carthage2017\/E5400650",
        "date_mesure_temp": "2020-05-01",
        "heure_mesure_temp": "00:00:00",
        "resultat": 11.1999998092651
    },
    {
        "code_station": "01097000",
        "libelle_station": "LA TERNOISE \u00c0 AUCHY LES HESDIN (62)",
        "localisation": "PONT DU CD 123",
        "uri_station": "https:\/\/id.eaufrance.fr\/StationMesureEauxSurface\/01097000",
        "longitude": 2.1026201,
        "latitude": 50.397567967,
        "code_commune": "62050",
        "libelle_commune": "Auchy-l\u00e8s-Hesdin",
        "code_cours_eau": "E5400650",
        "libelle_cours_eau": "Ternoise",
        "uri_cours_eau": "https:\/\/id.eaufrance.fr\/CoursEau_Carthage2017\/E5400650",
        "date_mesure_temp": "2020-06-01",
        "heure_mesure_temp": "00:00:00",
        "resultat": 12.8229999542236
    },
    {
        "code_station": "01097000",
        "libelle_station": "LA TERNOISE \u00c0 AUCHY LES HESDIN (62)",
        "localisation": "PONT DU CD 123",
        "uri_station": "https:\/\/id.eaufrance.fr\/StationMesureEauxSurface\/01097000",
        "longitude": 2.1026201,
        "latitude": 50.397567967,
        "code_commune": "62050",
        "libelle_commune": "Auchy-l\u00e8s-Hesdin",
        "code_cours_eau": "E5400650",
        "libelle_cours_eau": "Ternoise",
        "uri_cours_eau": "https:\/\/id.eaufrance.fr\/CoursEau_Carthage2017\/E5400650",
        "date_mesure_temp": "2020-07-01",
        "heure_mesure_temp": "00:00:00",
        "resultat": 12.4610004425049
    },
    {
        "code_station": "01097000",
        "libelle_station": "LA TERNOISE \u00c0 AUCHY LES HESDIN (62)",
        "localisation": "PONT DU CD 123",
        "uri_station": "https:\/\/id.eaufrance.fr\/StationMesureEauxSurface\/01097000",
        "longitude": 2.1026201,
        "latitude": 50.397567967,
        "code_commune": "62050",
        "libelle_commune": "Auchy-l\u00e8s-Hesdin",
        "code_cours_eau": "E5400650",
        "libelle_cours_eau": "Ternoise",
        "uri_cours_eau": "https:\/\/id.eaufrance.fr\/CoursEau_Carthage2017\/E5400650",
        "date_mesure_temp": "2020-08-01",
        "heure_mesure_temp": "00:00:00",
        "resultat": 13.9540004730225
    },
    {
        "code_station": "01097000",
        "libelle_station": "LA TERNOISE \u00c0 AUCHY LES HESDIN (62)",
        "localisation": "PONT DU CD 123",
        "uri_station": "https:\/\/id.eaufrance.fr\/StationMesureEauxSurface\/01097000",
        "longitude": 2.1026201,
        "latitude": 50.397567967,
        "code_commune": "62050",
        "libelle_commune": "Auchy-l\u00e8s-Hesdin",
        "code_cours_eau": "E5400650",
        "libelle_cours_eau": "Ternoise",
        "uri_cours_eau": "https:\/\/id.eaufrance.fr\/CoursEau_Carthage2017\/E5400650",
        "date_mesure_temp": "2020-09-01",
        "heure_mesure_temp": "00:00:00",
        "resultat": 12.1709995269775
    },
    {
        "code_station": "01097000",
        "libelle_station": "LA TERNOISE \u00c0 AUCHY LES HESDIN (62)",
        "localisation": "PONT DU CD 123",
        "uri_station": "https:\/\/id.eaufrance.fr\/StationMesureEauxSurface\/01097000",
        "longitude": 2.1026201,
        "latitude": 50.397567967,
        "code_commune": "62050",
        "libelle_commune": "Auchy-l\u00e8s-Hesdin",
        "code_cours_eau": "E5400650",
        "libelle_cours_eau": "Ternoise",
        "uri_cours_eau": "https:\/\/id.eaufrance.fr\/CoursEau_Carthage2017\/E5400650",
        "date_mesure_temp": "2020-10-01",
        "heure_mesure_temp": "00:00:00",
        "resultat": 12.3159999847412
    },
    {
        "code_station": "01097000",
        "libelle_station": "LA TERNOISE \u00c0 AUCHY LES HESDIN (62)",
        "localisation": "PONT DU CD 123",
        "uri_station": "https:\/\/id.eaufrance.fr\/StationMesureEauxSurface\/01097000",
        "longitude": 2.1026201,
        "latitude": 50.397567967,
        "code_commune": "62050",
        "libelle_commune": "Auchy-l\u00e8s-Hesdin",
        "code_cours_eau": "E5400650",
        "libelle_cours_eau": "Ternoise",
        "uri_cours_eau": "https:\/\/id.eaufrance.fr\/CoursEau_Carthage2017\/E5400650",
        "date_mesure_temp": "2020-11-01",
        "heure_mesure_temp": "00:00:00",
        "resultat": 11.6370000839233
    },
    {
        "code_station": "01097000",
        "libelle_station": "LA TERNOISE \u00c0 AUCHY LES HESDIN (62)",
        "localisation": "PONT DU CD 123",
        "uri_station": "https:\/\/id.eaufrance.fr\/StationMesureEauxSurface\/01097000",
        "longitude": 2.1026201,
        "latitude": 50.397567967,
        "code_commune": "62050",
        "libelle_commune": "Auchy-l\u00e8s-Hesdin",
        "code_cours_eau": "E5400650",
        "libelle_cours_eau": "Ternoise",
        "uri_cours_eau": "https:\/\/id.eaufrance.fr\/CoursEau_Carthage2017\/E5400650",
        "date_mesure_temp": "2020-12-01",
        "heure_mesure_temp": "00:00:00",
        "resultat": 9.95199966430664
    },
    {
        "code_station": "01097000",
        "libelle_station": "LA TERNOISE \u00c0 AUCHY LES HESDIN (62)",
        "localisation": "PONT DU CD 123",
        "uri_station": "https:\/\/id.eaufrance.fr\/StationMesureEauxSurface\/01097000",
        "longitude": 2.1026201,
        "latitude": 50.397567967,
        "code_commune": "62050",
        "libelle_commune": "Auchy-l\u00e8s-Hesdin",
        "code_cours_eau": "E5400650",
        "libelle_cours_eau": "Ternoise",
        "uri_cours_eau": "https:\/\/id.eaufrance.fr\/CoursEau_Carthage2017\/E5400650",
        "date_mesure_temp": "2021-01-01",
        "heure_mesure_temp": "00:00:00",
        "resultat": 8.96500015258789
    },
    {
        "code_station": "01097000",
        "libelle_station": "LA TERNOISE \u00c0 AUCHY LES HESDIN (62)",
        "localisation": "PONT DU CD 123",
        "uri_station": "https:\/\/id.eaufrance.fr\/StationMesureEauxSurface\/01097000",
        "longitude": 2.1026201,
        "latitude": 50.397567967,
        "code_commune": "62050",
        "libelle_commune": "Auchy-l\u00e8s-Hesdin",
        "code_cours_eau": "E5400650",
        "libelle_cours_eau": "Ternoise",
        "uri_cours_eau": "https:\/\/id.eaufrance.fr\/CoursEau_Carthage2017\/E5400650",
        "date_mesure_temp": "2021-02-01",
        "heure_mesure_temp": "00:00:00",
        "resultat": 9.26200008392334
    },
    {
        "code_station": "01097000",
        "libelle_station": "LA TERNOISE \u00c0 AUCHY LES HESDIN (62)",
        "localisation": "PONT DU CD 123",
        "uri_station": "https:\/\/id.eaufrance.fr\/StationMesureEauxSurface\/01097000",
        "longitude": 2.1026201,
        "latitude": 50.397567967,
        "code_commune": "62050",
        "libelle_commune": "Auchy-l\u00e8s-Hesdin",
        "code_cours_eau": "E5400650",
        "libelle_cours_eau": "Ternoise",
        "uri_cours_eau": "https:\/\/id.eaufrance.fr\/CoursEau_Carthage2017\/E5400650",
        "date_mesure_temp": "2021-03-01",
        "heure_mesure_temp": "00:00:00",
        "resultat": 10.0260000228882
    },
    {
        "code_station": "01097000",
        "libelle_station": "LA TERNOISE \u00c0 AUCHY LES HESDIN (62)",
        "localisation": "PONT DU CD 123",
        "uri_station": "https:\/\/id.eaufrance.fr\/StationMesureEauxSurface\/01097000",
        "longitude": 2.1026201,
        "latitude": 50.397567967,
        "code_commune": "62050",
        "libelle_commune": "Auchy-l\u00e8s-Hesdin",
        "code_cours_eau": "E5400650",
        "libelle_cours_eau": "Ternoise",
        "uri_cours_eau": "https:\/\/id.eaufrance.fr\/CoursEau_Carthage2017\/E5400650",
        "date_mesure_temp": "2021-04-01",
        "heure_mesure_temp": "00:00:00",
        "resultat": 12.0249996185303
    },
    {
        "code_station": "01097000",
        "libelle_station": "LA TERNOISE \u00c0 AUCHY LES HESDIN (62)",
        "localisation": "PONT DU CD 123",
        "uri_station": "https:\/\/id.eaufrance.fr\/StationMesureEauxSurface\/01097000",
        "longitude": 2.1026201,
        "latitude": 50.397567967,
        "code_commune": "62050",
        "libelle_commune": "Auchy-l\u00e8s-Hesdin",
        "code_cours_eau": "E5400650",
        "libelle_cours_eau": "Ternoise",
        "uri_cours_eau": "https:\/\/id.eaufrance.fr\/CoursEau_Carthage2017\/E5400650",
        "date_mesure_temp": "2021-05-01",
        "heure_mesure_temp": "00:00:00",
        "resultat": 10.6140003204346
    },
    {
        "code_station": "01097000",
        "libelle_station": "LA TERNOISE \u00c0 AUCHY LES HESDIN (62)",
        "localisation": "PONT DU CD 123",
        "uri_station": "https:\/\/id.eaufrance.fr\/StationMesureEauxSurface\/01097000",
        "longitude": 2.1026201,
        "latitude": 50.397567967,
        "code_commune": "62050",
        "libelle_commune": "Auchy-l\u00e8s-Hesdin",
        "code_cours_eau": "E5400650",
        "libelle_cours_eau": "Ternoise",
        "uri_cours_eau": "https:\/\/id.eaufrance.fr\/CoursEau_Carthage2017\/E5400650",
        "date_mesure_temp": "2021-06-01",
        "heure_mesure_temp": "00:00:00",
        "resultat": 13.0880002975464
    },
    {
        "code_station": "01097000",
        "libelle_station": "LA TERNOISE \u00c0 AUCHY LES HESDIN (62)",
        "localisation": "PONT DU CD 123",
        "uri_station": "https:\/\/id.eaufrance.fr\/StationMesureEauxSurface\/01097000",
        "longitude": 2.1026201,
        "latitude": 50.397567967,
        "code_commune": "62050",
        "libelle_commune": "Auchy-l\u00e8s-Hesdin",
        "code_cours_eau": "E5400650",
        "libelle_cours_eau": "Ternoise",
        "uri_cours_eau": "https:\/\/id.eaufrance.fr\/CoursEau_Carthage2017\/E5400650",
        "date_mesure_temp": "2021-07-01",
        "heure_mesure_temp": "00:00:00",
        "resultat": 12.2430000305176
    },
    {
        "code_station": "01097000",
        "libelle_station": "LA TERNOISE \u00c0 AUCHY LES HESDIN (62)",
        "localisation": "PONT DU CD 123",
        "uri_station": "https:\/\/id.eaufrance.fr\/StationMesureEauxSurface\/01097000",
        "longitude": 2.1026201,
        "latitude": 50.397567967,
        "code_commune": "62050",
        "libelle_commune": "Auchy-l\u00e8s-Hesdin",
        "code_cours_eau": "E5400650",
        "libelle_cours_eau": "Ternoise",
        "uri_cours_eau": "https:\/\/id.eaufrance.fr\/CoursEau_Carthage2017\/E5400650",
        "date_mesure_temp": "2021-08-01",
        "heure_mesure_temp": "00:00:00",
        "resultat": 12.9440002441406
    },
    {
        "code_station": "01097000",
        "libelle_station": "LA TERNOISE \u00c0 AUCHY LES HESDIN (62)",
        "localisation": "PONT DU CD 123",
        "uri_station": "https:\/\/id.eaufrance.fr\/StationMesureEauxSurface\/01097000",
        "longitude": 2.1026201,
        "latitude": 50.397567967,
        "code_commune": "62050",
        "libelle_commune": "Auchy-l\u00e8s-Hesdin",
        "code_cours_eau": "E5400650",
        "libelle_cours_eau": "Ternoise",
        "uri_cours_eau": "https:\/\/id.eaufrance.fr\/CoursEau_Carthage2017\/E5400650",
        "date_mesure_temp": "2021-09-01",
        "heure_mesure_temp": "00:00:00",
        "resultat": 12.6540002822876
    },
    {
        "code_station": "01097000",
        "libelle_station": "LA TERNOISE \u00c0 AUCHY LES HESDIN (62)",
        "localisation": "PONT DU CD 123",
        "uri_station": "https:\/\/id.eaufrance.fr\/StationMesureEauxSurface\/01097000",
        "longitude": 2.1026201,
        "latitude": 50.397567967,
        "code_commune": "62050",
        "libelle_commune": "Auchy-l\u00e8s-Hesdin",
        "code_cours_eau": "E5400650",
        "libelle_cours_eau": "Ternoise",
        "uri_cours_eau": "https:\/\/id.eaufrance.fr\/CoursEau_Carthage2017\/E5400650",
        "date_mesure_temp": "2021-10-01",
        "heure_mesure_temp": "00:00:00",
        "resultat": 11.1999998092651
    },
    {
        "code_station": "01097000",
        "libelle_station": "LA TERNOISE \u00c0 AUCHY LES HESDIN (62)",
        "localisation": "PONT DU CD 123",
        "uri_station": "https:\/\/id.eaufrance.fr\/StationMesureEauxSurface\/01097000",
        "longitude": 2.1026201,
        "latitude": 50.397567967,
        "code_commune": "62050",
        "libelle_commune": "Auchy-l\u00e8s-Hesdin",
        "code_cours_eau": "E5400650",
        "libelle_cours_eau": "Ternoise",
        "uri_cours_eau": "https:\/\/id.eaufrance.fr\/CoursEau_Carthage2017\/E5400650",
        "date_mesure_temp": "2021-11-01",
        "heure_mesure_temp": "00:00:00",
        "resultat": 10.7849998474121
    },
    {
        "code_station": "01097000",
        "libelle_station": "LA TERNOISE \u00c0 AUCHY LES HESDIN (62)",
        "localisation": "PONT DU CD 123",
        "uri_station": "https:\/\/id.eaufrance.fr\/StationMesureEauxSurface\/01097000",
        "longitude": 2.1026201,
        "latitude": 50.397567967,
        "code_commune": "62050",
        "libelle_commune": "Auchy-l\u00e8s-Hesdin",
        "code_cours_eau": "E5400650",
        "libelle_cours_eau": "Ternoise",
        "uri_cours_eau": "https:\/\/id.eaufrance.fr\/CoursEau_Carthage2017\/E5400650",
        "date_mesure_temp": "2021-12-01",
        "heure_mesure_temp": "00:00:00",
        "resultat": 10.1730003356934
    },
    {
        "code_station": "01097000",
        "libelle_station": "LA TERNOISE \u00c0 AUCHY LES HESDIN (62)",
        "localisation": "PONT DU CD 123",
        "uri_station": "https:\/\/id.eaufrance.fr\/StationMesureEauxSurface\/01097000",
        "longitude": 2.1026201,
        "latitude": 50.397567967,
        "code_commune": "62050",
        "libelle_commune": "Auchy-l\u00e8s-Hesdin",
        "code_cours_eau": "E5400650",
        "libelle_cours_eau": "Ternoise",
        "uri_cours_eau": "https:\/\/id.eaufrance.fr\/CoursEau_Carthage2017\/E5400650",
        "date_mesure_temp": "2022-01-01",
        "heure_mesure_temp": "00:00:00",
        "resultat": 11.0050001144409
    },
    {
        "code_station": "01097000",
        "libelle_station": "LA TERNOISE \u00c0 AUCHY LES HESDIN (62)",
        "localisation": "PONT DU CD 123",
        "uri_station": "https:\/\/id.eaufrance.fr\/StationMesureEauxSurface\/01097000",
        "longitude": 2.1026201,
        "latitude": 50.397567967,
        "code_commune": "62050",
        "libelle_commune": "Auchy-l\u00e8s-Hesdin",
        "code_cours_eau": "E5400650",
        "libelle_cours_eau": "Ternoise",
        "uri_cours_eau": "https:\/\/id.eaufrance.fr\/CoursEau_Carthage2017\/E5400650",
        "date_mesure_temp": "2022-02-01",
        "heure_mesure_temp": "00:00:00",
        "resultat": 8.96500015258789
    },
    {
        "code_station": "01097000",
        "libelle_station": "LA TERNOISE \u00c0 AUCHY LES HESDIN (62)",
        "localisation": "PONT DU CD 123",
        "uri_station": "https:\/\/id.eaufrance.fr\/StationMesureEauxSurface\/01097000",
        "longitude": 2.1026201,
        "latitude": 50.397567967,
        "code_commune": "62050",
        "libelle_commune": "Auchy-l\u00e8s-Hesdin",
        "code_cours_eau": "E5400650",
        "libelle_cours_eau": "Ternoise",
        "uri_cours_eau": "https:\/\/id.eaufrance.fr\/CoursEau_Carthage2017\/E5400650",
        "date_mesure_temp": "2022-03-01",
        "heure_mesure_temp": "00:00:00",
        "resultat": 9.6569995880127
    },
    {
        "code_station": "01097000",
        "libelle_station": "LA TERNOISE \u00c0 AUCHY LES HESDIN (62)",
        "localisation": "PONT DU CD 123",
        "uri_station": "https:\/\/id.eaufrance.fr\/StationMesureEauxSurface\/01097000",
        "longitude": 2.1026201,
        "latitude": 50.397567967,
        "code_commune": "62050",
        "libelle_commune": "Auchy-l\u00e8s-Hesdin",
        "code_cours_eau": "E5400650",
        "libelle_cours_eau": "Ternoise",
        "uri_cours_eau": "https:\/\/id.eaufrance.fr\/CoursEau_Carthage2017\/E5400650",
        "date_mesure_temp": "2022-04-01",
        "heure_mesure_temp": "00:00:00",
        "resultat": 9.23799991607666
    },
    {
        "code_station": "01097000",
        "libelle_station": "LA TERNOISE \u00c0 AUCHY LES HESDIN (62)",
        "localisation": "PONT DU CD 123",
        "uri_station": "https:\/\/id.eaufrance.fr\/StationMesureEauxSurface\/01097000",
        "longitude": 2.1026201,
        "latitude": 50.397567967,
        "code_commune": "62050",
        "libelle_commune": "Auchy-l\u00e8s-Hesdin",
        "code_cours_eau": "E5400650",
        "libelle_cours_eau": "Ternoise",
        "uri_cours_eau": "https:\/\/id.eaufrance.fr\/CoursEau_Carthage2017\/E5400650",
        "date_mesure_temp": "2022-05-01",
        "heure_mesure_temp": "00:00:00",
        "resultat": 11.2729997634888
    },
    {
        "code_station": "01097000",
        "libelle_station": "LA TERNOISE \u00c0 AUCHY LES HESDIN (62)",
        "localisation": "PONT DU CD 123",
        "uri_station": "https:\/\/id.eaufrance.fr\/StationMesureEauxSurface\/01097000",
        "longitude": 2.1026201,
        "latitude": 50.397567967,
        "code_commune": "62050",
        "libelle_commune": "Auchy-l\u00e8s-Hesdin",
        "code_cours_eau": "E5400650",
        "libelle_cours_eau": "Ternoise",
        "uri_cours_eau": "https:\/\/id.eaufrance.fr\/CoursEau_Carthage2017\/E5400650",
        "date_mesure_temp": "2022-06-01",
        "heure_mesure_temp": "00:00:00",
        "resultat": 11.8800001144409
    },
    {
        "code_station": "01097000",
        "libelle_station": "LA TERNOISE \u00c0 AUCHY LES HESDIN (62)",
        "localisation": "PONT DU CD 123",
        "uri_station": "https:\/\/id.eaufrance.fr\/StationMesureEauxSurface\/01097000",
        "longitude": 2.1026201,
        "latitude": 50.397567967,
        "code_commune": "62050",
        "libelle_commune": "Auchy-l\u00e8s-Hesdin",
        "code_cours_eau": "E5400650",
        "libelle_cours_eau": "Ternoise",
        "uri_cours_eau": "https:\/\/id.eaufrance.fr\/CoursEau_Carthage2017\/E5400650",
        "date_mesure_temp": "2022-07-01",
        "heure_mesure_temp": "00:00:00",
        "resultat": 12.0500001907349
    },
    {
        "code_station": "01097000",
        "libelle_station": "LA TERNOISE \u00c0 AUCHY LES HESDIN (62)",
        "localisation": "PONT DU CD 123",
        "uri_station": "https:\/\/id.eaufrance.fr\/StationMesureEauxSurface\/01097000",
        "longitude": 2.1026201,
        "latitude": 50.397567967,
        "code_commune": "62050",
        "libelle_commune": "Auchy-l\u00e8s-Hesdin",
        "code_cours_eau": "E5400650",
        "libelle_cours_eau": "Ternoise",
        "uri_cours_eau": "https:\/\/id.eaufrance.fr\/CoursEau_Carthage2017\/E5400650",
        "date_mesure_temp": "2022-08-01",
        "heure_mesure_temp": "00:00:00",
        "resultat": 13.3290004730225
    },
    {
        "code_station": "01097000",
        "libelle_station": "LA TERNOISE \u00c0 AUCHY LES HESDIN (62)",
        "localisation": "PONT DU CD 123",
        "uri_station": "https:\/\/id.eaufrance.fr\/StationMesureEauxSurface\/01097000",
        "longitude": 2.1026201,
        "latitude": 50.397567967,
        "code_commune": "62050",
        "libelle_commune": "Auchy-l\u00e8s-Hesdin",
        "code_cours_eau": "E5400650",
        "libelle_cours_eau": "Ternoise",
        "uri_cours_eau": "https:\/\/id.eaufrance.fr\/CoursEau_Carthage2017\/E5400650",
        "date_mesure_temp": "2022-09-01",
        "heure_mesure_temp": "00:00:00",
        "resultat": 13.4969997406006
    },
    {
        "code_station": "01097000",
        "libelle_station": "LA TERNOISE \u00c0 AUCHY LES HESDIN (62)",
        "localisation": "PONT DU CD 123",
        "uri_station": "https:\/\/id.eaufrance.fr\/StationMesureEauxSurface\/01097000",
        "longitude": 2.1026201,
        "latitude": 50.397567967,
        "code_commune": "62050",
        "libelle_commune": "Auchy-l\u00e8s-Hesdin",
        "code_cours_eau": "E5400650",
        "libelle_cours_eau": "Ternoise",
        "uri_cours_eau": "https:\/\/id.eaufrance.fr\/CoursEau_Carthage2017\/E5400650",
        "date_mesure_temp": "2022-10-01",
        "heure_mesure_temp": "00:00:00",
        "resultat": 11.2729997634888
    },
    {
        "code_station": "01097000",
        "libelle_station": "LA TERNOISE \u00c0 AUCHY LES HESDIN (62)",
        "localisation": "PONT DU CD 123",
        "uri_station": "https:\/\/id.eaufrance.fr\/StationMesureEauxSurface\/01097000",
        "longitude": 2.1026201,
        "latitude": 50.397567967,
        "code_commune": "62050",
        "libelle_commune": "Auchy-l\u00e8s-Hesdin",
        "code_cours_eau": "E5400650",
        "libelle_cours_eau": "Ternoise",
        "uri_cours_eau": "https:\/\/id.eaufrance.fr\/CoursEau_Carthage2017\/E5400650",
        "date_mesure_temp": "2022-11-01",
        "heure_mesure_temp": "00:00:00",
        "resultat": 11.8559999465942
    }
]