[
    {
        "code_station": "04043800",
        "libelle_station": "QUEUNE \u00e0 SOUVIGNY",
        "localisation": "PRELEVEMENT EN AVAL DE LA PASSERELLE ET DU GUE",
        "uri_station": "https:\/\/id.eaufrance.fr\/StationMesureEauxSurface\/04043800",
        "longitude": 3.211251384,
        "latitude": 46.536002961,
        "code_commune": "03275",
        "libelle_commune": "Souvigny",
        "code_cours_eau": "K3464000",
        "libelle_cours_eau": "la Queune",
        "uri_cours_eau": "https:\/\/id.eaufrance.fr\/CoursEau_Carthage2017\/K3464000",
        "date_mesure_temp": "2008-11-13",
        "heure_mesure_temp": "10:19:28",
        "resultat": 11.88
    },
    {
        "code_station": "04043800",
        "libelle_station": "QUEUNE \u00e0 SOUVIGNY",
        "localisation": "PRELEVEMENT EN AVAL DE LA PASSERELLE ET DU GUE",
        "uri_station": "https:\/\/id.eaufrance.fr\/StationMesureEauxSurface\/04043800",
        "longitude": 3.211251384,
        "latitude": 46.536002961,
        "code_commune": "03275",
        "libelle_commune": "Souvigny",
        "code_cours_eau": "K3464000",
        "libelle_cours_eau": "la Queune",
        "uri_cours_eau": "https:\/\/id.eaufrance.fr\/CoursEau_Carthage2017\/K3464000",
        "date_mesure_temp": "2008-12-01",
        "heure_mesure_temp": "00:19:28",
        "resultat": 4.818
    },
    {
        "code_station": "04043800",
        "libelle_station": "QUEUNE \u00e0 SOUVIGNY",
        "localisation": "PRELEVEMENT EN AVAL DE LA PASSERELLE ET DU GUE",
        "uri_station": "https:\/\/id.eaufrance.fr\/StationMesureEauxSurface\/04043800",
        "longitude": 3.211251384,
        "latitude": 46.536002961,
        "code_commune": "03275",
        "libelle_commune": "Souvigny",
        "code_cours_eau": "K3464000",
        "libelle_cours_eau": "la Queune",
        "uri_cours_eau": "https:\/\/id.eaufrance.fr\/CoursEau_Carthage2017\/K3464000",
        "date_mesure_temp": "2009-01-01",
        "heure_mesure_temp": "00:19:28",
        "resultat": 3.142
    },
    {
        "code_station": "04043800",
        "libelle_station": "QUEUNE \u00e0 SOUVIGNY",
        "localisation": "PRELEVEMENT EN AVAL DE LA PASSERELLE ET DU GUE",
        "uri_station": "https:\/\/id.eaufrance.fr\/StationMesureEauxSurface\/04043800",
        "longitude": 3.211251384,
        "latitude": 46.536002961,
        "code_commune": "03275",
        "libelle_commune": "Souvigny",
        "code_cours_eau": "K3464000",
        "libelle_cours_eau": "la Queune",
        "uri_cours_eau": "https:\/\/id.eaufrance.fr\/CoursEau_Carthage2017\/K3464000",
        "date_mesure_temp": "2009-02-01",
        "heure_mesure_temp": "00:19:28",
        "resultat": 3.063
    },
    {
        "code_station": "04043800",
        "libelle_station": "QUEUNE \u00e0 SOUVIGNY",
        "localisation": "PRELEVEMENT EN AVAL DE LA PASSERELLE ET DU GUE",
        "uri_station": "https:\/\/id.eaufrance.fr\/StationMesureEauxSurface\/04043800",
        "longitude": 3.211251384,
        "latitude": 46.536002961,
        "code_commune": "03275",
        "libelle_commune": "Souvigny",
        "code_cours_eau": "K3464000",
        "libelle_cours_eau": "la Queune",
        "uri_cours_eau": "https:\/\/id.eaufrance.fr\/CoursEau_Carthage2017\/K3464000",
        "date_mesure_temp": "2009-03-01",
        "heure_mesure_temp": "00:19:28",
        "resultat": 6.839
    },
    {
        "code_station": "04043800",
        "libelle_station": "QUEUNE \u00e0 SOUVIGNY",
        "localisation": "PRELEVEMENT EN AVAL DE LA PASSERELLE ET DU GUE",
        "uri_station": "https:\/\/id.eaufrance.fr\/StationMesureEauxSurface\/04043800",
        "longitude": 3.211251384,
        "latitude": 46.536002961,
        "code_commune": "03275",
        "libelle_commune": "Souvigny",
        "code_cours_eau": "K3464000",
        "libelle_cours_eau": "la Queune",
        "uri_cours_eau": "https:\/\/id.eaufrance.fr\/CoursEau_Carthage2017\/K3464000",
        "date_mesure_temp": "2009-04-01",
        "heure_mesure_temp": "00:19:28",
        "resultat": 8.916
    },
    {
        "code_station": "04043800",
        "libelle_station": "QUEUNE \u00e0 SOUVIGNY",
        "localisation": "PRELEVEMENT EN AVAL DE LA PASSERELLE ET DU GUE",
        "uri_station": "https:\/\/id.eaufrance.fr\/StationMesureEauxSurface\/04043800",
        "longitude": 3.211251384,
        "latitude": 46.536002961,
        "code_commune": "03275",
        "libelle_commune": "Souvigny",
        "code_cours_eau": "K3464000",
        "libelle_cours_eau": "la Queune",
        "uri_cours_eau": "https:\/\/id.eaufrance.fr\/CoursEau_Carthage2017\/K3464000",
        "date_mesure_temp": "2009-05-01",
        "heure_mesure_temp": "00:19:28",
        "resultat": 12.727
    },
    {
        "code_station": "04043800",
        "libelle_station": "QUEUNE \u00e0 SOUVIGNY",
        "localisation": "PRELEVEMENT EN AVAL DE LA PASSERELLE ET DU GUE",
        "uri_station": "https:\/\/id.eaufrance.fr\/StationMesureEauxSurface\/04043800",
        "longitude": 3.211251384,
        "latitude": 46.536002961,
        "code_commune": "03275",
        "libelle_commune": "Souvigny",
        "code_cours_eau": "K3464000",
        "libelle_cours_eau": "la Queune",
        "uri_cours_eau": "https:\/\/id.eaufrance.fr\/CoursEau_Carthage2017\/K3464000",
        "date_mesure_temp": "2009-06-01",
        "heure_mesure_temp": "00:19:28",
        "resultat": 16.034
    },
    {
        "code_station": "04043800",
        "libelle_station": "QUEUNE \u00e0 SOUVIGNY",
        "localisation": "PRELEVEMENT EN AVAL DE LA PASSERELLE ET DU GUE",
        "uri_station": "https:\/\/id.eaufrance.fr\/StationMesureEauxSurface\/04043800",
        "longitude": 3.211251384,
        "latitude": 46.536002961,
        "code_commune": "03275",
        "libelle_commune": "Souvigny",
        "code_cours_eau": "K3464000",
        "libelle_cours_eau": "la Queune",
        "uri_cours_eau": "https:\/\/id.eaufrance.fr\/CoursEau_Carthage2017\/K3464000",
        "date_mesure_temp": "2009-07-01",
        "heure_mesure_temp": "00:19:28",
        "resultat": 20.46
    },
    {
        "code_station": "04043800",
        "libelle_station": "QUEUNE \u00e0 SOUVIGNY",
        "localisation": "PRELEVEMENT EN AVAL DE LA PASSERELLE ET DU GUE",
        "uri_station": "https:\/\/id.eaufrance.fr\/StationMesureEauxSurface\/04043800",
        "longitude": 3.211251384,
        "latitude": 46.536002961,
        "code_commune": "03275",
        "libelle_commune": "Souvigny",
        "code_cours_eau": "K3464000",
        "libelle_cours_eau": "la Queune",
        "uri_cours_eau": "https:\/\/id.eaufrance.fr\/CoursEau_Carthage2017\/K3464000",
        "date_mesure_temp": "2009-08-01",
        "heure_mesure_temp": "00:19:28",
        "resultat": 17.272
    },
    {
        "code_station": "04043800",
        "libelle_station": "QUEUNE \u00e0 SOUVIGNY",
        "localisation": "PRELEVEMENT EN AVAL DE LA PASSERELLE ET DU GUE",
        "uri_station": "https:\/\/id.eaufrance.fr\/StationMesureEauxSurface\/04043800",
        "longitude": 3.211251384,
        "latitude": 46.536002961,
        "code_commune": "03275",
        "libelle_commune": "Souvigny",
        "code_cours_eau": "K3464000",
        "libelle_cours_eau": "la Queune",
        "uri_cours_eau": "https:\/\/id.eaufrance.fr\/CoursEau_Carthage2017\/K3464000",
        "date_mesure_temp": "2009-09-01",
        "heure_mesure_temp": "00:19:28",
        "resultat": 16.272
    },
    {
        "code_station": "04043800",
        "libelle_station": "QUEUNE \u00e0 SOUVIGNY",
        "localisation": "PRELEVEMENT EN AVAL DE LA PASSERELLE ET DU GUE",
        "uri_station": "https:\/\/id.eaufrance.fr\/StationMesureEauxSurface\/04043800",
        "longitude": 3.211251384,
        "latitude": 46.536002961,
        "code_commune": "03275",
        "libelle_commune": "Souvigny",
        "code_cours_eau": "K3464000",
        "libelle_cours_eau": "la Queune",
        "uri_cours_eau": "https:\/\/id.eaufrance.fr\/CoursEau_Carthage2017\/K3464000",
        "date_mesure_temp": "2009-10-01",
        "heure_mesure_temp": "00:19:28",
        "resultat": 13.281
    },
    {
        "code_station": "04043800",
        "libelle_station": "QUEUNE \u00e0 SOUVIGNY",
        "localisation": "PRELEVEMENT EN AVAL DE LA PASSERELLE ET DU GUE",
        "uri_station": "https:\/\/id.eaufrance.fr\/StationMesureEauxSurface\/04043800",
        "longitude": 3.211251384,
        "latitude": 46.536002961,
        "code_commune": "03275",
        "libelle_commune": "Souvigny",
        "code_cours_eau": "K3464000",
        "libelle_cours_eau": "la Queune",
        "uri_cours_eau": "https:\/\/id.eaufrance.fr\/CoursEau_Carthage2017\/K3464000",
        "date_mesure_temp": "2009-11-01",
        "heure_mesure_temp": "00:19:28",
        "resultat": 10.075
    },
    {
        "code_station": "04043800",
        "libelle_station": "QUEUNE \u00e0 SOUVIGNY",
        "localisation": "PRELEVEMENT EN AVAL DE LA PASSERELLE ET DU GUE",
        "uri_station": "https:\/\/id.eaufrance.fr\/StationMesureEauxSurface\/04043800",
        "longitude": 3.211251384,
        "latitude": 46.536002961,
        "code_commune": "03275",
        "libelle_commune": "Souvigny",
        "code_cours_eau": "K3464000",
        "libelle_cours_eau": "la Queune",
        "uri_cours_eau": "https:\/\/id.eaufrance.fr\/CoursEau_Carthage2017\/K3464000",
        "date_mesure_temp": "2009-12-01",
        "heure_mesure_temp": "00:19:28",
        "resultat": 8.469
    },
    {
        "code_station": "04043800",
        "libelle_station": "QUEUNE \u00e0 SOUVIGNY",
        "localisation": "PRELEVEMENT EN AVAL DE LA PASSERELLE ET DU GUE",
        "uri_station": "https:\/\/id.eaufrance.fr\/StationMesureEauxSurface\/04043800",
        "longitude": 3.211251384,
        "latitude": 46.536002961,
        "code_commune": "03275",
        "libelle_commune": "Souvigny",
        "code_cours_eau": "K3464000",
        "libelle_cours_eau": "la Queune",
        "uri_cours_eau": "https:\/\/id.eaufrance.fr\/CoursEau_Carthage2017\/K3464000",
        "date_mesure_temp": "2010-01-01",
        "heure_mesure_temp": "00:19:28",
        "resultat": 6.484
    },
    {
        "code_station": "04043800",
        "libelle_station": "QUEUNE \u00e0 SOUVIGNY",
        "localisation": "PRELEVEMENT EN AVAL DE LA PASSERELLE ET DU GUE",
        "uri_station": "https:\/\/id.eaufrance.fr\/StationMesureEauxSurface\/04043800",
        "longitude": 3.211251384,
        "latitude": 46.536002961,
        "code_commune": "03275",
        "libelle_commune": "Souvigny",
        "code_cours_eau": "K3464000",
        "libelle_cours_eau": "la Queune",
        "uri_cours_eau": "https:\/\/id.eaufrance.fr\/CoursEau_Carthage2017\/K3464000",
        "date_mesure_temp": "2010-02-01",
        "heure_mesure_temp": "00:19:28",
        "resultat": 0.77
    },
    {
        "code_station": "04043800",
        "libelle_station": "QUEUNE \u00e0 SOUVIGNY",
        "localisation": "PRELEVEMENT EN AVAL DE LA PASSERELLE ET DU GUE",
        "uri_station": "https:\/\/id.eaufrance.fr\/StationMesureEauxSurface\/04043800",
        "longitude": 3.211251384,
        "latitude": 46.536002961,
        "code_commune": "03275",
        "libelle_commune": "Souvigny",
        "code_cours_eau": "K3464000",
        "libelle_cours_eau": "la Queune",
        "uri_cours_eau": "https:\/\/id.eaufrance.fr\/CoursEau_Carthage2017\/K3464000",
        "date_mesure_temp": "2010-03-01",
        "heure_mesure_temp": "00:19:28",
        "resultat": 7.393
    },
    {
        "code_station": "04043800",
        "libelle_station": "QUEUNE \u00e0 SOUVIGNY",
        "localisation": "PRELEVEMENT EN AVAL DE LA PASSERELLE ET DU GUE",
        "uri_station": "https:\/\/id.eaufrance.fr\/StationMesureEauxSurface\/04043800",
        "longitude": 3.211251384,
        "latitude": 46.536002961,
        "code_commune": "03275",
        "libelle_commune": "Souvigny",
        "code_cours_eau": "K3464000",
        "libelle_cours_eau": "la Queune",
        "uri_cours_eau": "https:\/\/id.eaufrance.fr\/CoursEau_Carthage2017\/K3464000",
        "date_mesure_temp": "2010-04-01",
        "heure_mesure_temp": "00:19:28",
        "resultat": 9.312
    },
    {
        "code_station": "04043800",
        "libelle_station": "QUEUNE \u00e0 SOUVIGNY",
        "localisation": "PRELEVEMENT EN AVAL DE LA PASSERELLE ET DU GUE",
        "uri_station": "https:\/\/id.eaufrance.fr\/StationMesureEauxSurface\/04043800",
        "longitude": 3.211251384,
        "latitude": 46.536002961,
        "code_commune": "03275",
        "libelle_commune": "Souvigny",
        "code_cours_eau": "K3464000",
        "libelle_cours_eau": "la Queune",
        "uri_cours_eau": "https:\/\/id.eaufrance.fr\/CoursEau_Carthage2017\/K3464000",
        "date_mesure_temp": "2010-05-01",
        "heure_mesure_temp": "00:19:28",
        "resultat": 14.768
    },
    {
        "code_station": "04043800",
        "libelle_station": "QUEUNE \u00e0 SOUVIGNY",
        "localisation": "PRELEVEMENT EN AVAL DE LA PASSERELLE ET DU GUE",
        "uri_station": "https:\/\/id.eaufrance.fr\/StationMesureEauxSurface\/04043800",
        "longitude": 3.211251384,
        "latitude": 46.536002961,
        "code_commune": "03275",
        "libelle_commune": "Souvigny",
        "code_cours_eau": "K3464000",
        "libelle_cours_eau": "la Queune",
        "uri_cours_eau": "https:\/\/id.eaufrance.fr\/CoursEau_Carthage2017\/K3464000",
        "date_mesure_temp": "2010-06-01",
        "heure_mesure_temp": "00:19:28",
        "resultat": 16.153
    },
    {
        "code_station": "04043800",
        "libelle_station": "QUEUNE \u00e0 SOUVIGNY",
        "localisation": "PRELEVEMENT EN AVAL DE LA PASSERELLE ET DU GUE",
        "uri_station": "https:\/\/id.eaufrance.fr\/StationMesureEauxSurface\/04043800",
        "longitude": 3.211251384,
        "latitude": 46.536002961,
        "code_commune": "03275",
        "libelle_commune": "Souvigny",
        "code_cours_eau": "K3464000",
        "libelle_cours_eau": "la Queune",
        "uri_cours_eau": "https:\/\/id.eaufrance.fr\/CoursEau_Carthage2017\/K3464000",
        "date_mesure_temp": "2010-07-01",
        "heure_mesure_temp": "00:19:28",
        "resultat": 20.579
    },
    {
        "code_station": "04043800",
        "libelle_station": "QUEUNE \u00e0 SOUVIGNY",
        "localisation": "PRELEVEMENT EN AVAL DE LA PASSERELLE ET DU GUE",
        "uri_station": "https:\/\/id.eaufrance.fr\/StationMesureEauxSurface\/04043800",
        "longitude": 3.211251384,
        "latitude": 46.536002961,
        "code_commune": "03275",
        "libelle_commune": "Souvigny",
        "code_cours_eau": "K3464000",
        "libelle_cours_eau": "la Queune",
        "uri_cours_eau": "https:\/\/id.eaufrance.fr\/CoursEau_Carthage2017\/K3464000",
        "date_mesure_temp": "2010-08-01",
        "heure_mesure_temp": "00:19:28",
        "resultat": 18.152
    },
    {
        "code_station": "04043800",
        "libelle_station": "QUEUNE \u00e0 SOUVIGNY",
        "localisation": "PRELEVEMENT EN AVAL DE LA PASSERELLE ET DU GUE",
        "uri_station": "https:\/\/id.eaufrance.fr\/StationMesureEauxSurface\/04043800",
        "longitude": 3.211251384,
        "latitude": 46.536002961,
        "code_commune": "03275",
        "libelle_commune": "Souvigny",
        "code_cours_eau": "K3464000",
        "libelle_cours_eau": "la Queune",
        "uri_cours_eau": "https:\/\/id.eaufrance.fr\/CoursEau_Carthage2017\/K3464000",
        "date_mesure_temp": "2010-09-01",
        "heure_mesure_temp": "00:19:28",
        "resultat": 14.697
    },
    {
        "code_station": "04043800",
        "libelle_station": "QUEUNE \u00e0 SOUVIGNY",
        "localisation": "PRELEVEMENT EN AVAL DE LA PASSERELLE ET DU GUE",
        "uri_station": "https:\/\/id.eaufrance.fr\/StationMesureEauxSurface\/04043800",
        "longitude": 3.211251384,
        "latitude": 46.536002961,
        "code_commune": "03275",
        "libelle_commune": "Souvigny",
        "code_cours_eau": "K3464000",
        "libelle_cours_eau": "la Queune",
        "uri_cours_eau": "https:\/\/id.eaufrance.fr\/CoursEau_Carthage2017\/K3464000",
        "date_mesure_temp": "2010-10-01",
        "heure_mesure_temp": "00:19:28",
        "resultat": 12.389
    },
    {
        "code_station": "04043800",
        "libelle_station": "QUEUNE \u00e0 SOUVIGNY",
        "localisation": "PRELEVEMENT EN AVAL DE LA PASSERELLE ET DU GUE",
        "uri_station": "https:\/\/id.eaufrance.fr\/StationMesureEauxSurface\/04043800",
        "longitude": 3.211251384,
        "latitude": 46.536002961,
        "code_commune": "03275",
        "libelle_commune": "Souvigny",
        "code_cours_eau": "K3464000",
        "libelle_cours_eau": "la Queune",
        "uri_cours_eau": "https:\/\/id.eaufrance.fr\/CoursEau_Carthage2017\/K3464000",
        "date_mesure_temp": "2010-11-01",
        "heure_mesure_temp": "00:19:28",
        "resultat": 10.001
    },
    {
        "code_station": "04043800",
        "libelle_station": "QUEUNE \u00e0 SOUVIGNY",
        "localisation": "PRELEVEMENT EN AVAL DE LA PASSERELLE ET DU GUE",
        "uri_station": "https:\/\/id.eaufrance.fr\/StationMesureEauxSurface\/04043800",
        "longitude": 3.211251384,
        "latitude": 46.536002961,
        "code_commune": "03275",
        "libelle_commune": "Souvigny",
        "code_cours_eau": "K3464000",
        "libelle_cours_eau": "la Queune",
        "uri_cours_eau": "https:\/\/id.eaufrance.fr\/CoursEau_Carthage2017\/K3464000",
        "date_mesure_temp": "2010-12-01",
        "heure_mesure_temp": "00:19:28",
        "resultat": 3.063
    },
    {
        "code_station": "04043800",
        "libelle_station": "QUEUNE \u00e0 SOUVIGNY",
        "localisation": "PRELEVEMENT EN AVAL DE LA PASSERELLE ET DU GUE",
        "uri_station": "https:\/\/id.eaufrance.fr\/StationMesureEauxSurface\/04043800",
        "longitude": 3.211251384,
        "latitude": 46.536002961,
        "code_commune": "03275",
        "libelle_commune": "Souvigny",
        "code_cours_eau": "K3464000",
        "libelle_cours_eau": "la Queune",
        "uri_cours_eau": "https:\/\/id.eaufrance.fr\/CoursEau_Carthage2017\/K3464000",
        "date_mesure_temp": "2011-01-01",
        "heure_mesure_temp": "00:19:28",
        "resultat": 4.662
    },
    {
        "code_station": "04043800",
        "libelle_station": "QUEUNE \u00e0 SOUVIGNY",
        "localisation": "PRELEVEMENT EN AVAL DE LA PASSERELLE ET DU GUE",
        "uri_station": "https:\/\/id.eaufrance.fr\/StationMesureEauxSurface\/04043800",
        "longitude": 3.211251384,
        "latitude": 46.536002961,
        "code_commune": "03275",
        "libelle_commune": "Souvigny",
        "code_cours_eau": "K3464000",
        "libelle_cours_eau": "la Queune",
        "uri_cours_eau": "https:\/\/id.eaufrance.fr\/CoursEau_Carthage2017\/K3464000",
        "date_mesure_temp": "2011-02-01",
        "heure_mesure_temp": "00:19:28",
        "resultat": 1.724
    },
    {
        "code_station": "04043800",
        "libelle_station": "QUEUNE \u00e0 SOUVIGNY",
        "localisation": "PRELEVEMENT EN AVAL DE LA PASSERELLE ET DU GUE",
        "uri_station": "https:\/\/id.eaufrance.fr\/StationMesureEauxSurface\/04043800",
        "longitude": 3.211251384,
        "latitude": 46.536002961,
        "code_commune": "03275",
        "libelle_commune": "Souvigny",
        "code_cours_eau": "K3464000",
        "libelle_cours_eau": "la Queune",
        "uri_cours_eau": "https:\/\/id.eaufrance.fr\/CoursEau_Carthage2017\/K3464000",
        "date_mesure_temp": "2011-03-01",
        "heure_mesure_temp": "00:19:28",
        "resultat": 6.636
    },
    {
        "code_station": "04043800",
        "libelle_station": "QUEUNE \u00e0 SOUVIGNY",
        "localisation": "PRELEVEMENT EN AVAL DE LA PASSERELLE ET DU GUE",
        "uri_station": "https:\/\/id.eaufrance.fr\/StationMesureEauxSurface\/04043800",
        "longitude": 3.211251384,
        "latitude": 46.536002961,
        "code_commune": "03275",
        "libelle_commune": "Souvigny",
        "code_cours_eau": "K3464000",
        "libelle_cours_eau": "la Queune",
        "uri_cours_eau": "https:\/\/id.eaufrance.fr\/CoursEau_Carthage2017\/K3464000",
        "date_mesure_temp": "2011-04-01",
        "heure_mesure_temp": "00:19:28",
        "resultat": 12.171
    },
    {
        "code_station": "04043800",
        "libelle_station": "QUEUNE \u00e0 SOUVIGNY",
        "localisation": "PRELEVEMENT EN AVAL DE LA PASSERELLE ET DU GUE",
        "uri_station": "https:\/\/id.eaufrance.fr\/StationMesureEauxSurface\/04043800",
        "longitude": 3.211251384,
        "latitude": 46.536002961,
        "code_commune": "03275",
        "libelle_commune": "Souvigny",
        "code_cours_eau": "K3464000",
        "libelle_cours_eau": "la Queune",
        "uri_cours_eau": "https:\/\/id.eaufrance.fr\/CoursEau_Carthage2017\/K3464000",
        "date_mesure_temp": "2011-05-01",
        "heure_mesure_temp": "00:19:28",
        "resultat": 13.233
    },
    {
        "code_station": "04043800",
        "libelle_station": "QUEUNE \u00e0 SOUVIGNY",
        "localisation": "PRELEVEMENT EN AVAL DE LA PASSERELLE ET DU GUE",
        "uri_station": "https:\/\/id.eaufrance.fr\/StationMesureEauxSurface\/04043800",
        "longitude": 3.211251384,
        "latitude": 46.536002961,
        "code_commune": "03275",
        "libelle_commune": "Souvigny",
        "code_cours_eau": "K3464000",
        "libelle_cours_eau": "la Queune",
        "uri_cours_eau": "https:\/\/id.eaufrance.fr\/CoursEau_Carthage2017\/K3464000",
        "date_mesure_temp": "2011-06-01",
        "heure_mesure_temp": "00:19:28",
        "resultat": 14.05
    },
    {
        "code_station": "04043800",
        "libelle_station": "QUEUNE \u00e0 SOUVIGNY",
        "localisation": "PRELEVEMENT EN AVAL DE LA PASSERELLE ET DU GUE",
        "uri_station": "https:\/\/id.eaufrance.fr\/StationMesureEauxSurface\/04043800",
        "longitude": 3.211251384,
        "latitude": 46.536002961,
        "code_commune": "03275",
        "libelle_commune": "Souvigny",
        "code_cours_eau": "K3464000",
        "libelle_cours_eau": "la Queune",
        "uri_cours_eau": "https:\/\/id.eaufrance.fr\/CoursEau_Carthage2017\/K3464000",
        "date_mesure_temp": "2011-07-01",
        "heure_mesure_temp": "00:19:28",
        "resultat": 16.082
    },
    {
        "code_station": "04043800",
        "libelle_station": "QUEUNE \u00e0 SOUVIGNY",
        "localisation": "PRELEVEMENT EN AVAL DE LA PASSERELLE ET DU GUE",
        "uri_station": "https:\/\/id.eaufrance.fr\/StationMesureEauxSurface\/04043800",
        "longitude": 3.211251384,
        "latitude": 46.536002961,
        "code_commune": "03275",
        "libelle_commune": "Souvigny",
        "code_cours_eau": "K3464000",
        "libelle_cours_eau": "la Queune",
        "uri_cours_eau": "https:\/\/id.eaufrance.fr\/CoursEau_Carthage2017\/K3464000",
        "date_mesure_temp": "2011-08-01",
        "heure_mesure_temp": "00:19:28",
        "resultat": 15.652
    },
    {
        "code_station": "04043800",
        "libelle_station": "QUEUNE \u00e0 SOUVIGNY",
        "localisation": "PRELEVEMENT EN AVAL DE LA PASSERELLE ET DU GUE",
        "uri_station": "https:\/\/id.eaufrance.fr\/StationMesureEauxSurface\/04043800",
        "longitude": 3.211251384,
        "latitude": 46.536002961,
        "code_commune": "03275",
        "libelle_commune": "Souvigny",
        "code_cours_eau": "K3464000",
        "libelle_cours_eau": "la Queune",
        "uri_cours_eau": "https:\/\/id.eaufrance.fr\/CoursEau_Carthage2017\/K3464000",
        "date_mesure_temp": "2011-09-01",
        "heure_mesure_temp": "00:19:28",
        "resultat": 14.673
    },
    {
        "code_station": "04043800",
        "libelle_station": "QUEUNE \u00e0 SOUVIGNY",
        "localisation": "PRELEVEMENT EN AVAL DE LA PASSERELLE ET DU GUE",
        "uri_station": "https:\/\/id.eaufrance.fr\/StationMesureEauxSurface\/04043800",
        "longitude": 3.211251384,
        "latitude": 46.536002961,
        "code_commune": "03275",
        "libelle_commune": "Souvigny",
        "code_cours_eau": "K3464000",
        "libelle_cours_eau": "la Queune",
        "uri_cours_eau": "https:\/\/id.eaufrance.fr\/CoursEau_Carthage2017\/K3464000",
        "date_mesure_temp": "2011-10-01",
        "heure_mesure_temp": "00:19:28",
        "resultat": 14.361
    },
    {
        "code_station": "04043800",
        "libelle_station": "QUEUNE \u00e0 SOUVIGNY",
        "localisation": "PRELEVEMENT EN AVAL DE LA PASSERELLE ET DU GUE",
        "uri_station": "https:\/\/id.eaufrance.fr\/StationMesureEauxSurface\/04043800",
        "longitude": 3.211251384,
        "latitude": 46.536002961,
        "code_commune": "03275",
        "libelle_commune": "Souvigny",
        "code_cours_eau": "K3464000",
        "libelle_cours_eau": "la Queune",
        "uri_cours_eau": "https:\/\/id.eaufrance.fr\/CoursEau_Carthage2017\/K3464000",
        "date_mesure_temp": "2011-11-01",
        "heure_mesure_temp": "00:19:28",
        "resultat": 11.224
    },
    {
        "code_station": "04043800",
        "libelle_station": "QUEUNE \u00e0 SOUVIGNY",
        "localisation": "PRELEVEMENT EN AVAL DE LA PASSERELLE ET DU GUE",
        "uri_station": "https:\/\/id.eaufrance.fr\/StationMesureEauxSurface\/04043800",
        "longitude": 3.211251384,
        "latitude": 46.536002961,
        "code_commune": "03275",
        "libelle_commune": "Souvigny",
        "code_cours_eau": "K3464000",
        "libelle_cours_eau": "la Queune",
        "uri_cours_eau": "https:\/\/id.eaufrance.fr\/CoursEau_Carthage2017\/K3464000",
        "date_mesure_temp": "2011-12-01",
        "heure_mesure_temp": "00:19:28",
        "resultat": 8.693
    },
    {
        "code_station": "04043800",
        "libelle_station": "QUEUNE \u00e0 SOUVIGNY",
        "localisation": "PRELEVEMENT EN AVAL DE LA PASSERELLE ET DU GUE",
        "uri_station": "https:\/\/id.eaufrance.fr\/StationMesureEauxSurface\/04043800",
        "longitude": 3.211251384,
        "latitude": 46.536002961,
        "code_commune": "03275",
        "libelle_commune": "Souvigny",
        "code_cours_eau": "K3464000",
        "libelle_cours_eau": "la Queune",
        "uri_cours_eau": "https:\/\/id.eaufrance.fr\/CoursEau_Carthage2017\/K3464000",
        "date_mesure_temp": "2012-01-01",
        "heure_mesure_temp": "00:19:28",
        "resultat": 8.965
    },
    {
        "code_station": "04043800",
        "libelle_station": "QUEUNE \u00e0 SOUVIGNY",
        "localisation": "PRELEVEMENT EN AVAL DE LA PASSERELLE ET DU GUE",
        "uri_station": "https:\/\/id.eaufrance.fr\/StationMesureEauxSurface\/04043800",
        "longitude": 3.211251384,
        "latitude": 46.536002961,
        "code_commune": "03275",
        "libelle_commune": "Souvigny",
        "code_cours_eau": "K3464000",
        "libelle_cours_eau": "la Queune",
        "uri_cours_eau": "https:\/\/id.eaufrance.fr\/CoursEau_Carthage2017\/K3464000",
        "date_mesure_temp": "2012-02-01",
        "heure_mesure_temp": "00:19:28",
        "resultat": 3.38
    },
    {
        "code_station": "04043800",
        "libelle_station": "QUEUNE \u00e0 SOUVIGNY",
        "localisation": "PRELEVEMENT EN AVAL DE LA PASSERELLE ET DU GUE",
        "uri_station": "https:\/\/id.eaufrance.fr\/StationMesureEauxSurface\/04043800",
        "longitude": 3.211251384,
        "latitude": 46.536002961,
        "code_commune": "03275",
        "libelle_commune": "Souvigny",
        "code_cours_eau": "K3464000",
        "libelle_cours_eau": "la Queune",
        "uri_cours_eau": "https:\/\/id.eaufrance.fr\/CoursEau_Carthage2017\/K3464000",
        "date_mesure_temp": "2012-03-01",
        "heure_mesure_temp": "00:19:28",
        "resultat": 5.514
    },
    {
        "code_station": "04043800",
        "libelle_station": "QUEUNE \u00e0 SOUVIGNY",
        "localisation": "PRELEVEMENT EN AVAL DE LA PASSERELLE ET DU GUE",
        "uri_station": "https:\/\/id.eaufrance.fr\/StationMesureEauxSurface\/04043800",
        "longitude": 3.211251384,
        "latitude": 46.536002961,
        "code_commune": "03275",
        "libelle_commune": "Souvigny",
        "code_cours_eau": "K3464000",
        "libelle_cours_eau": "la Queune",
        "uri_cours_eau": "https:\/\/id.eaufrance.fr\/CoursEau_Carthage2017\/K3464000",
        "date_mesure_temp": "2012-04-01",
        "heure_mesure_temp": "00:19:28",
        "resultat": 11.492
    },
    {
        "code_station": "04043800",
        "libelle_station": "QUEUNE \u00e0 SOUVIGNY",
        "localisation": "PRELEVEMENT EN AVAL DE LA PASSERELLE ET DU GUE",
        "uri_station": "https:\/\/id.eaufrance.fr\/StationMesureEauxSurface\/04043800",
        "longitude": 3.211251384,
        "latitude": 46.536002961,
        "code_commune": "03275",
        "libelle_commune": "Souvigny",
        "code_cours_eau": "K3464000",
        "libelle_cours_eau": "la Queune",
        "uri_cours_eau": "https:\/\/id.eaufrance.fr\/CoursEau_Carthage2017\/K3464000",
        "date_mesure_temp": "2012-05-01",
        "heure_mesure_temp": "00:19:28",
        "resultat": 12.485
    },
    {
        "code_station": "04043800",
        "libelle_station": "QUEUNE \u00e0 SOUVIGNY",
        "localisation": "PRELEVEMENT EN AVAL DE LA PASSERELLE ET DU GUE",
        "uri_station": "https:\/\/id.eaufrance.fr\/StationMesureEauxSurface\/04043800",
        "longitude": 3.211251384,
        "latitude": 46.536002961,
        "code_commune": "03275",
        "libelle_commune": "Souvigny",
        "code_cours_eau": "K3464000",
        "libelle_cours_eau": "la Queune",
        "uri_cours_eau": "https:\/\/id.eaufrance.fr\/CoursEau_Carthage2017\/K3464000",
        "date_mesure_temp": "2012-06-01",
        "heure_mesure_temp": "00:19:28",
        "resultat": 19.246
    },
    {
        "code_station": "04043800",
        "libelle_station": "QUEUNE \u00e0 SOUVIGNY",
        "localisation": "PRELEVEMENT EN AVAL DE LA PASSERELLE ET DU GUE",
        "uri_station": "https:\/\/id.eaufrance.fr\/StationMesureEauxSurface\/04043800",
        "longitude": 3.211251384,
        "latitude": 46.536002961,
        "code_commune": "03275",
        "libelle_commune": "Souvigny",
        "code_cours_eau": "K3464000",
        "libelle_cours_eau": "la Queune",
        "uri_cours_eau": "https:\/\/id.eaufrance.fr\/CoursEau_Carthage2017\/K3464000",
        "date_mesure_temp": "2012-07-01",
        "heure_mesure_temp": "00:19:28",
        "resultat": 19.603
    },
    {
        "code_station": "04043800",
        "libelle_station": "QUEUNE \u00e0 SOUVIGNY",
        "localisation": "PRELEVEMENT EN AVAL DE LA PASSERELLE ET DU GUE",
        "uri_station": "https:\/\/id.eaufrance.fr\/StationMesureEauxSurface\/04043800",
        "longitude": 3.211251384,
        "latitude": 46.536002961,
        "code_commune": "03275",
        "libelle_commune": "Souvigny",
        "code_cours_eau": "K3464000",
        "libelle_cours_eau": "la Queune",
        "uri_cours_eau": "https:\/\/id.eaufrance.fr\/CoursEau_Carthage2017\/K3464000",
        "date_mesure_temp": "2012-08-01",
        "heure_mesure_temp": "00:19:28",
        "resultat": 18.485
    },
    {
        "code_station": "04043800",
        "libelle_station": "QUEUNE \u00e0 SOUVIGNY",
        "localisation": "PRELEVEMENT EN AVAL DE LA PASSERELLE ET DU GUE",
        "uri_station": "https:\/\/id.eaufrance.fr\/StationMesureEauxSurface\/04043800",
        "longitude": 3.211251384,
        "latitude": 46.536002961,
        "code_commune": "03275",
        "libelle_commune": "Souvigny",
        "code_cours_eau": "K3464000",
        "libelle_cours_eau": "la Queune",
        "uri_cours_eau": "https:\/\/id.eaufrance.fr\/CoursEau_Carthage2017\/K3464000",
        "date_mesure_temp": "2012-09-01",
        "heure_mesure_temp": "00:19:28",
        "resultat": 15.27
    },
    {
        "code_station": "04043800",
        "libelle_station": "QUEUNE \u00e0 SOUVIGNY",
        "localisation": "PRELEVEMENT EN AVAL DE LA PASSERELLE ET DU GUE",
        "uri_station": "https:\/\/id.eaufrance.fr\/StationMesureEauxSurface\/04043800",
        "longitude": 3.211251384,
        "latitude": 46.536002961,
        "code_commune": "03275",
        "libelle_commune": "Souvigny",
        "code_cours_eau": "K3464000",
        "libelle_cours_eau": "la Queune",
        "uri_cours_eau": "https:\/\/id.eaufrance.fr\/CoursEau_Carthage2017\/K3464000",
        "date_mesure_temp": "2012-10-01",
        "heure_mesure_temp": "00:19:28",
        "resultat": 12.195
    },
    {
        "code_station": "04043800",
        "libelle_station": "QUEUNE \u00e0 SOUVIGNY",
        "localisation": "PRELEVEMENT EN AVAL DE LA PASSERELLE ET DU GUE",
        "uri_station": "https:\/\/id.eaufrance.fr\/StationMesureEauxSurface\/04043800",
        "longitude": 3.211251384,
        "latitude": 46.536002961,
        "code_commune": "03275",
        "libelle_commune": "Souvigny",
        "code_cours_eau": "K3464000",
        "libelle_cours_eau": "la Queune",
        "uri_cours_eau": "https:\/\/id.eaufrance.fr\/CoursEau_Carthage2017\/K3464000",
        "date_mesure_temp": "2012-11-01",
        "heure_mesure_temp": "00:19:28",
        "resultat": 7.393
    },
    {
        "code_station": "04043800",
        "libelle_station": "QUEUNE \u00e0 SOUVIGNY",
        "localisation": "PRELEVEMENT EN AVAL DE LA PASSERELLE ET DU GUE",
        "uri_station": "https:\/\/id.eaufrance.fr\/StationMesureEauxSurface\/04043800",
        "longitude": 3.211251384,
        "latitude": 46.536002961,
        "code_commune": "03275",
        "libelle_commune": "Souvigny",
        "code_cours_eau": "K3464000",
        "libelle_cours_eau": "la Queune",
        "uri_cours_eau": "https:\/\/id.eaufrance.fr\/CoursEau_Carthage2017\/K3464000",
        "date_mesure_temp": "2012-12-01",
        "heure_mesure_temp": "00:19:28",
        "resultat": 5.898
    },
    {
        "code_station": "04043800",
        "libelle_station": "QUEUNE \u00e0 SOUVIGNY",
        "localisation": "PRELEVEMENT EN AVAL DE LA PASSERELLE ET DU GUE",
        "uri_station": "https:\/\/id.eaufrance.fr\/StationMesureEauxSurface\/04043800",
        "longitude": 3.211251384,
        "latitude": 46.536002961,
        "code_commune": "03275",
        "libelle_commune": "Souvigny",
        "code_cours_eau": "K3464000",
        "libelle_cours_eau": "la Queune",
        "uri_cours_eau": "https:\/\/id.eaufrance.fr\/CoursEau_Carthage2017\/K3464000",
        "date_mesure_temp": "2013-01-01",
        "heure_mesure_temp": "00:19:28",
        "resultat": 6.611
    },
    {
        "code_station": "04043800",
        "libelle_station": "QUEUNE \u00e0 SOUVIGNY",
        "localisation": "PRELEVEMENT EN AVAL DE LA PASSERELLE ET DU GUE",
        "uri_station": "https:\/\/id.eaufrance.fr\/StationMesureEauxSurface\/04043800",
        "longitude": 3.211251384,
        "latitude": 46.536002961,
        "code_commune": "03275",
        "libelle_commune": "Souvigny",
        "code_cours_eau": "K3464000",
        "libelle_cours_eau": "la Queune",
        "uri_cours_eau": "https:\/\/id.eaufrance.fr\/CoursEau_Carthage2017\/K3464000",
        "date_mesure_temp": "2013-02-01",
        "heure_mesure_temp": "00:19:28",
        "resultat": 7.695
    },
    {
        "code_station": "04043800",
        "libelle_station": "QUEUNE \u00e0 SOUVIGNY",
        "localisation": "PRELEVEMENT EN AVAL DE LA PASSERELLE ET DU GUE",
        "uri_station": "https:\/\/id.eaufrance.fr\/StationMesureEauxSurface\/04043800",
        "longitude": 3.211251384,
        "latitude": 46.536002961,
        "code_commune": "03275",
        "libelle_commune": "Souvigny",
        "code_cours_eau": "K3464000",
        "libelle_cours_eau": "la Queune",
        "uri_cours_eau": "https:\/\/id.eaufrance.fr\/CoursEau_Carthage2017\/K3464000",
        "date_mesure_temp": "2013-03-01",
        "heure_mesure_temp": "00:19:28",
        "resultat": 4.272
    },
    {
        "code_station": "04043800",
        "libelle_station": "QUEUNE \u00e0 SOUVIGNY",
        "localisation": "PRELEVEMENT EN AVAL DE LA PASSERELLE ET DU GUE",
        "uri_station": "https:\/\/id.eaufrance.fr\/StationMesureEauxSurface\/04043800",
        "longitude": 3.211251384,
        "latitude": 46.536002961,
        "code_commune": "03275",
        "libelle_commune": "Souvigny",
        "code_cours_eau": "K3464000",
        "libelle_cours_eau": "la Queune",
        "uri_cours_eau": "https:\/\/id.eaufrance.fr\/CoursEau_Carthage2017\/K3464000",
        "date_mesure_temp": "2013-04-01",
        "heure_mesure_temp": "00:19:28",
        "resultat": 7.82
    },
    {
        "code_station": "04043800",
        "libelle_station": "QUEUNE \u00e0 SOUVIGNY",
        "localisation": "PRELEVEMENT EN AVAL DE LA PASSERELLE ET DU GUE",
        "uri_station": "https:\/\/id.eaufrance.fr\/StationMesureEauxSurface\/04043800",
        "longitude": 3.211251384,
        "latitude": 46.536002961,
        "code_commune": "03275",
        "libelle_commune": "Souvigny",
        "code_cours_eau": "K3464000",
        "libelle_cours_eau": "la Queune",
        "uri_cours_eau": "https:\/\/id.eaufrance.fr\/CoursEau_Carthage2017\/K3464000",
        "date_mesure_temp": "2013-05-01",
        "heure_mesure_temp": "00:19:28",
        "resultat": 11.929
    },
    {
        "code_station": "04043800",
        "libelle_station": "QUEUNE \u00e0 SOUVIGNY",
        "localisation": "PRELEVEMENT EN AVAL DE LA PASSERELLE ET DU GUE",
        "uri_station": "https:\/\/id.eaufrance.fr\/StationMesureEauxSurface\/04043800",
        "longitude": 3.211251384,
        "latitude": 46.536002961,
        "code_commune": "03275",
        "libelle_commune": "Souvigny",
        "code_cours_eau": "K3464000",
        "libelle_cours_eau": "la Queune",
        "uri_cours_eau": "https:\/\/id.eaufrance.fr\/CoursEau_Carthage2017\/K3464000",
        "date_mesure_temp": "2013-06-01",
        "heure_mesure_temp": "00:19:28",
        "resultat": 12.243
    },
    {
        "code_station": "04043800",
        "libelle_station": "QUEUNE \u00e0 SOUVIGNY",
        "localisation": "PRELEVEMENT EN AVAL DE LA PASSERELLE ET DU GUE",
        "uri_station": "https:\/\/id.eaufrance.fr\/StationMesureEauxSurface\/04043800",
        "longitude": 3.211251384,
        "latitude": 46.536002961,
        "code_commune": "03275",
        "libelle_commune": "Souvigny",
        "code_cours_eau": "K3464000",
        "libelle_cours_eau": "la Queune",
        "uri_cours_eau": "https:\/\/id.eaufrance.fr\/CoursEau_Carthage2017\/K3464000",
        "date_mesure_temp": "2013-07-01",
        "heure_mesure_temp": "00:19:28",
        "resultat": 15.533
    },
    {
        "code_station": "04043800",
        "libelle_station": "QUEUNE \u00e0 SOUVIGNY",
        "localisation": "PRELEVEMENT EN AVAL DE LA PASSERELLE ET DU GUE",
        "uri_station": "https:\/\/id.eaufrance.fr\/StationMesureEauxSurface\/04043800",
        "longitude": 3.211251384,
        "latitude": 46.536002961,
        "code_commune": "03275",
        "libelle_commune": "Souvigny",
        "code_cours_eau": "K3464000",
        "libelle_cours_eau": "la Queune",
        "uri_cours_eau": "https:\/\/id.eaufrance.fr\/CoursEau_Carthage2017\/K3464000",
        "date_mesure_temp": "2013-08-01",
        "heure_mesure_temp": "00:19:28",
        "resultat": 20.079
    },
    {
        "code_station": "04043800",
        "libelle_station": "QUEUNE \u00e0 SOUVIGNY",
        "localisation": "PRELEVEMENT EN AVAL DE LA PASSERELLE ET DU GUE",
        "uri_station": "https:\/\/id.eaufrance.fr\/StationMesureEauxSurface\/04043800",
        "longitude": 3.211251384,
        "latitude": 46.536002961,
        "code_commune": "03275",
        "libelle_commune": "Souvigny",
        "code_cours_eau": "K3464000",
        "libelle_cours_eau": "la Queune",
        "uri_cours_eau": "https:\/\/id.eaufrance.fr\/CoursEau_Carthage2017\/K3464000",
        "date_mesure_temp": "2013-09-01",
        "heure_mesure_temp": "00:19:28",
        "resultat": 15.605
    },
    {
        "code_station": "04043800",
        "libelle_station": "QUEUNE \u00e0 SOUVIGNY",
        "localisation": "PRELEVEMENT EN AVAL DE LA PASSERELLE ET DU GUE",
        "uri_station": "https:\/\/id.eaufrance.fr\/StationMesureEauxSurface\/04043800",
        "longitude": 3.211251384,
        "latitude": 46.536002961,
        "code_commune": "03275",
        "libelle_commune": "Souvigny",
        "code_cours_eau": "K3464000",
        "libelle_cours_eau": "la Queune",
        "uri_cours_eau": "https:\/\/id.eaufrance.fr\/CoursEau_Carthage2017\/K3464000",
        "date_mesure_temp": "2013-10-01",
        "heure_mesure_temp": "00:19:28",
        "resultat": 15.7
    },
    {
        "code_station": "04043800",
        "libelle_station": "QUEUNE \u00e0 SOUVIGNY",
        "localisation": "PRELEVEMENT EN AVAL DE LA PASSERELLE ET DU GUE",
        "uri_station": "https:\/\/id.eaufrance.fr\/StationMesureEauxSurface\/04043800",
        "longitude": 3.211251384,
        "latitude": 46.536002961,
        "code_commune": "03275",
        "libelle_commune": "Souvigny",
        "code_cours_eau": "K3464000",
        "libelle_cours_eau": "la Queune",
        "uri_cours_eau": "https:\/\/id.eaufrance.fr\/CoursEau_Carthage2017\/K3464000",
        "date_mesure_temp": "2013-11-01",
        "heure_mesure_temp": "00:19:28",
        "resultat": 8.593
    },
    {
        "code_station": "04043800",
        "libelle_station": "QUEUNE \u00e0 SOUVIGNY",
        "localisation": "PRELEVEMENT EN AVAL DE LA PASSERELLE ET DU GUE",
        "uri_station": "https:\/\/id.eaufrance.fr\/StationMesureEauxSurface\/04043800",
        "longitude": 3.211251384,
        "latitude": 46.536002961,
        "code_commune": "03275",
        "libelle_commune": "Souvigny",
        "code_cours_eau": "K3464000",
        "libelle_cours_eau": "la Queune",
        "uri_cours_eau": "https:\/\/id.eaufrance.fr\/CoursEau_Carthage2017\/K3464000",
        "date_mesure_temp": "2013-12-01",
        "heure_mesure_temp": "00:19:28",
        "resultat": 4.714
    },
    {
        "code_station": "04043800",
        "libelle_station": "QUEUNE \u00e0 SOUVIGNY",
        "localisation": "PRELEVEMENT EN AVAL DE LA PASSERELLE ET DU GUE",
        "uri_station": "https:\/\/id.eaufrance.fr\/StationMesureEauxSurface\/04043800",
        "longitude": 3.211251384,
        "latitude": 46.536002961,
        "code_commune": "03275",
        "libelle_commune": "Souvigny",
        "code_cours_eau": "K3464000",
        "libelle_cours_eau": "la Queune",
        "uri_cours_eau": "https:\/\/id.eaufrance.fr\/CoursEau_Carthage2017\/K3464000",
        "date_mesure_temp": "2014-01-01",
        "heure_mesure_temp": "00:19:28",
        "resultat": 4.71400022506714
    },
    {
        "code_station": "04043800",
        "libelle_station": "QUEUNE \u00e0 SOUVIGNY",
        "localisation": "PRELEVEMENT EN AVAL DE LA PASSERELLE ET DU GUE",
        "uri_station": "https:\/\/id.eaufrance.fr\/StationMesureEauxSurface\/04043800",
        "longitude": 3.211251384,
        "latitude": 46.536002961,
        "code_commune": "03275",
        "libelle_commune": "Souvigny",
        "code_cours_eau": "K3464000",
        "libelle_cours_eau": "la Queune",
        "uri_cours_eau": "https:\/\/id.eaufrance.fr\/CoursEau_Carthage2017\/K3464000",
        "date_mesure_temp": "2014-02-01",
        "heure_mesure_temp": "00:19:28",
        "resultat": 5.25699996948242
    },
    {
        "code_station": "04043800",
        "libelle_station": "QUEUNE \u00e0 SOUVIGNY",
        "localisation": "PRELEVEMENT EN AVAL DE LA PASSERELLE ET DU GUE",
        "uri_station": "https:\/\/id.eaufrance.fr\/StationMesureEauxSurface\/04043800",
        "longitude": 3.211251384,
        "latitude": 46.536002961,
        "code_commune": "03275",
        "libelle_commune": "Souvigny",
        "code_cours_eau": "K3464000",
        "libelle_cours_eau": "la Queune",
        "uri_cours_eau": "https:\/\/id.eaufrance.fr\/CoursEau_Carthage2017\/K3464000",
        "date_mesure_temp": "2014-03-01",
        "heure_mesure_temp": "00:19:28",
        "resultat": 6.81300020217896
    },
    {
        "code_station": "04043800",
        "libelle_station": "QUEUNE \u00e0 SOUVIGNY",
        "localisation": "PRELEVEMENT EN AVAL DE LA PASSERELLE ET DU GUE",
        "uri_station": "https:\/\/id.eaufrance.fr\/StationMesureEauxSurface\/04043800",
        "longitude": 3.211251384,
        "latitude": 46.536002961,
        "code_commune": "03275",
        "libelle_commune": "Souvigny",
        "code_cours_eau": "K3464000",
        "libelle_cours_eau": "la Queune",
        "uri_cours_eau": "https:\/\/id.eaufrance.fr\/CoursEau_Carthage2017\/K3464000",
        "date_mesure_temp": "2014-04-01",
        "heure_mesure_temp": "00:19:28",
        "resultat": 10.9320001602173
    },
    {
        "code_station": "04043800",
        "libelle_station": "QUEUNE \u00e0 SOUVIGNY",
        "localisation": "PRELEVEMENT EN AVAL DE LA PASSERELLE ET DU GUE",
        "uri_station": "https:\/\/id.eaufrance.fr\/StationMesureEauxSurface\/04043800",
        "longitude": 3.211251384,
        "latitude": 46.536002961,
        "code_commune": "03275",
        "libelle_commune": "Souvigny",
        "code_cours_eau": "K3464000",
        "libelle_cours_eau": "la Queune",
        "uri_cours_eau": "https:\/\/id.eaufrance.fr\/CoursEau_Carthage2017\/K3464000",
        "date_mesure_temp": "2014-05-01",
        "heure_mesure_temp": "00:19:28",
        "resultat": 11.8070001602173
    },
    {
        "code_station": "04043800",
        "libelle_station": "QUEUNE \u00e0 SOUVIGNY",
        "localisation": "PRELEVEMENT EN AVAL DE LA PASSERELLE ET DU GUE",
        "uri_station": "https:\/\/id.eaufrance.fr\/StationMesureEauxSurface\/04043800",
        "longitude": 3.211251384,
        "latitude": 46.536002961,
        "code_commune": "03275",
        "libelle_commune": "Souvigny",
        "code_cours_eau": "K3464000",
        "libelle_cours_eau": "la Queune",
        "uri_cours_eau": "https:\/\/id.eaufrance.fr\/CoursEau_Carthage2017\/K3464000",
        "date_mesure_temp": "2014-06-01",
        "heure_mesure_temp": "00:19:28",
        "resultat": 13.8339996337891
    },
    {
        "code_station": "04043800",
        "libelle_station": "QUEUNE \u00e0 SOUVIGNY",
        "localisation": "PRELEVEMENT EN AVAL DE LA PASSERELLE ET DU GUE",
        "uri_station": "https:\/\/id.eaufrance.fr\/StationMesureEauxSurface\/04043800",
        "longitude": 3.211251384,
        "latitude": 46.536002961,
        "code_commune": "03275",
        "libelle_commune": "Souvigny",
        "code_cours_eau": "K3464000",
        "libelle_cours_eau": "la Queune",
        "uri_cours_eau": "https:\/\/id.eaufrance.fr\/CoursEau_Carthage2017\/K3464000",
        "date_mesure_temp": "2014-07-01",
        "heure_mesure_temp": "00:19:28",
        "resultat": 15.293999671936
    },
    {
        "code_station": "04043800",
        "libelle_station": "QUEUNE \u00e0 SOUVIGNY",
        "localisation": "PRELEVEMENT EN AVAL DE LA PASSERELLE ET DU GUE",
        "uri_station": "https:\/\/id.eaufrance.fr\/StationMesureEauxSurface\/04043800",
        "longitude": 3.211251384,
        "latitude": 46.536002961,
        "code_commune": "03275",
        "libelle_commune": "Souvigny",
        "code_cours_eau": "K3464000",
        "libelle_cours_eau": "la Queune",
        "uri_cours_eau": "https:\/\/id.eaufrance.fr\/CoursEau_Carthage2017\/K3464000",
        "date_mesure_temp": "2014-08-01",
        "heure_mesure_temp": "00:19:28",
        "resultat": 18.3659992218018
    },
    {
        "code_station": "04043800",
        "libelle_station": "QUEUNE \u00e0 SOUVIGNY",
        "localisation": "PRELEVEMENT EN AVAL DE LA PASSERELLE ET DU GUE",
        "uri_station": "https:\/\/id.eaufrance.fr\/StationMesureEauxSurface\/04043800",
        "longitude": 3.211251384,
        "latitude": 46.536002961,
        "code_commune": "03275",
        "libelle_commune": "Souvigny",
        "code_cours_eau": "K3464000",
        "libelle_cours_eau": "la Queune",
        "uri_cours_eau": "https:\/\/id.eaufrance.fr\/CoursEau_Carthage2017\/K3464000",
        "date_mesure_temp": "2014-09-01",
        "heure_mesure_temp": "00:19:28",
        "resultat": 16.5820007324219
    },
    {
        "code_station": "04043800",
        "libelle_station": "QUEUNE \u00e0 SOUVIGNY",
        "localisation": "PRELEVEMENT EN AVAL DE LA PASSERELLE ET DU GUE",
        "uri_station": "https:\/\/id.eaufrance.fr\/StationMesureEauxSurface\/04043800",
        "longitude": 3.211251384,
        "latitude": 46.536002961,
        "code_commune": "03275",
        "libelle_commune": "Souvigny",
        "code_cours_eau": "K3464000",
        "libelle_cours_eau": "la Queune",
        "uri_cours_eau": "https:\/\/id.eaufrance.fr\/CoursEau_Carthage2017\/K3464000",
        "date_mesure_temp": "2014-10-01",
        "heure_mesure_temp": "00:19:28",
        "resultat": 15.1269998550415
    },
    {
        "code_station": "04043800",
        "libelle_station": "QUEUNE \u00e0 SOUVIGNY",
        "localisation": "PRELEVEMENT EN AVAL DE LA PASSERELLE ET DU GUE",
        "uri_station": "https:\/\/id.eaufrance.fr\/StationMesureEauxSurface\/04043800",
        "longitude": 3.211251384,
        "latitude": 46.536002961,
        "code_commune": "03275",
        "libelle_commune": "Souvigny",
        "code_cours_eau": "K3464000",
        "libelle_cours_eau": "la Queune",
        "uri_cours_eau": "https:\/\/id.eaufrance.fr\/CoursEau_Carthage2017\/K3464000",
        "date_mesure_temp": "2014-11-01",
        "heure_mesure_temp": "00:19:28",
        "resultat": 11.1510000228882
    },
    {
        "code_station": "04043800",
        "libelle_station": "QUEUNE \u00e0 SOUVIGNY",
        "localisation": "PRELEVEMENT EN AVAL DE LA PASSERELLE ET DU GUE",
        "uri_station": "https:\/\/id.eaufrance.fr\/StationMesureEauxSurface\/04043800",
        "longitude": 3.211251384,
        "latitude": 46.536002961,
        "code_commune": "03275",
        "libelle_commune": "Souvigny",
        "code_cours_eau": "K3464000",
        "libelle_cours_eau": "la Queune",
        "uri_cours_eau": "https:\/\/id.eaufrance.fr\/CoursEau_Carthage2017\/K3464000",
        "date_mesure_temp": "2014-12-01",
        "heure_mesure_temp": "00:19:28",
        "resultat": 8.84099960327148
    },
    {
        "code_station": "04043800",
        "libelle_station": "QUEUNE \u00e0 SOUVIGNY",
        "localisation": "PRELEVEMENT EN AVAL DE LA PASSERELLE ET DU GUE",
        "uri_station": "https:\/\/id.eaufrance.fr\/StationMesureEauxSurface\/04043800",
        "longitude": 3.211251384,
        "latitude": 46.536002961,
        "code_commune": "03275",
        "libelle_commune": "Souvigny",
        "code_cours_eau": "K3464000",
        "libelle_cours_eau": "la Queune",
        "uri_cours_eau": "https:\/\/id.eaufrance.fr\/CoursEau_Carthage2017\/K3464000",
        "date_mesure_temp": "2015-01-01",
        "heure_mesure_temp": "00:19:28",
        "resultat": 3.48499989509583
    },
    {
        "code_station": "04043800",
        "libelle_station": "QUEUNE \u00e0 SOUVIGNY",
        "localisation": "PRELEVEMENT EN AVAL DE LA PASSERELLE ET DU GUE",
        "uri_station": "https:\/\/id.eaufrance.fr\/StationMesureEauxSurface\/04043800",
        "longitude": 3.211251384,
        "latitude": 46.536002961,
        "code_commune": "03275",
        "libelle_commune": "Souvigny",
        "code_cours_eau": "K3464000",
        "libelle_cours_eau": "la Queune",
        "uri_cours_eau": "https:\/\/id.eaufrance.fr\/CoursEau_Carthage2017\/K3464000",
        "date_mesure_temp": "2015-02-01",
        "heure_mesure_temp": "00:19:28",
        "resultat": 4.58400011062622
    },
    {
        "code_station": "04043800",
        "libelle_station": "QUEUNE \u00e0 SOUVIGNY",
        "localisation": "PRELEVEMENT EN AVAL DE LA PASSERELLE ET DU GUE",
        "uri_station": "https:\/\/id.eaufrance.fr\/StationMesureEauxSurface\/04043800",
        "longitude": 3.211251384,
        "latitude": 46.536002961,
        "code_commune": "03275",
        "libelle_commune": "Souvigny",
        "code_cours_eau": "K3464000",
        "libelle_cours_eau": "la Queune",
        "uri_cours_eau": "https:\/\/id.eaufrance.fr\/CoursEau_Carthage2017\/K3464000",
        "date_mesure_temp": "2015-03-01",
        "heure_mesure_temp": "00:19:28",
        "resultat": 6.23000001907349
    },
    {
        "code_station": "04043800",
        "libelle_station": "QUEUNE \u00e0 SOUVIGNY",
        "localisation": "PRELEVEMENT EN AVAL DE LA PASSERELLE ET DU GUE",
        "uri_station": "https:\/\/id.eaufrance.fr\/StationMesureEauxSurface\/04043800",
        "longitude": 3.211251384,
        "latitude": 46.536002961,
        "code_commune": "03275",
        "libelle_commune": "Souvigny",
        "code_cours_eau": "K3464000",
        "libelle_cours_eau": "la Queune",
        "uri_cours_eau": "https:\/\/id.eaufrance.fr\/CoursEau_Carthage2017\/K3464000",
        "date_mesure_temp": "2015-04-01",
        "heure_mesure_temp": "00:19:28",
        "resultat": 11.2729997634888
    },
    {
        "code_station": "04043800",
        "libelle_station": "QUEUNE \u00e0 SOUVIGNY",
        "localisation": "PRELEVEMENT EN AVAL DE LA PASSERELLE ET DU GUE",
        "uri_station": "https:\/\/id.eaufrance.fr\/StationMesureEauxSurface\/04043800",
        "longitude": 3.211251384,
        "latitude": 46.536002961,
        "code_commune": "03275",
        "libelle_commune": "Souvigny",
        "code_cours_eau": "K3464000",
        "libelle_cours_eau": "la Queune",
        "uri_cours_eau": "https:\/\/id.eaufrance.fr\/CoursEau_Carthage2017\/K3464000",
        "date_mesure_temp": "2015-05-01",
        "heure_mesure_temp": "00:19:28",
        "resultat": 12.4370002746582
    },
    {
        "code_station": "04043800",
        "libelle_station": "QUEUNE \u00e0 SOUVIGNY",
        "localisation": "PRELEVEMENT EN AVAL DE LA PASSERELLE ET DU GUE",
        "uri_station": "https:\/\/id.eaufrance.fr\/StationMesureEauxSurface\/04043800",
        "longitude": 3.211251384,
        "latitude": 46.536002961,
        "code_commune": "03275",
        "libelle_commune": "Souvigny",
        "code_cours_eau": "K3464000",
        "libelle_cours_eau": "la Queune",
        "uri_cours_eau": "https:\/\/id.eaufrance.fr\/CoursEau_Carthage2017\/K3464000",
        "date_mesure_temp": "2015-06-01",
        "heure_mesure_temp": "00:19:28",
        "resultat": 15.2700004577637
    },
    {
        "code_station": "04043800",
        "libelle_station": "QUEUNE \u00e0 SOUVIGNY",
        "localisation": "PRELEVEMENT EN AVAL DE LA PASSERELLE ET DU GUE",
        "uri_station": "https:\/\/id.eaufrance.fr\/StationMesureEauxSurface\/04043800",
        "longitude": 3.211251384,
        "latitude": 46.536002961,
        "code_commune": "03275",
        "libelle_commune": "Souvigny",
        "code_cours_eau": "K3464000",
        "libelle_cours_eau": "la Queune",
        "uri_cours_eau": "https:\/\/id.eaufrance.fr\/CoursEau_Carthage2017\/K3464000",
        "date_mesure_temp": "2015-07-01",
        "heure_mesure_temp": "00:19:28",
        "resultat": 20.6030006408691
    },
    {
        "code_station": "04043800",
        "libelle_station": "QUEUNE \u00e0 SOUVIGNY",
        "localisation": "PRELEVEMENT EN AVAL DE LA PASSERELLE ET DU GUE",
        "uri_station": "https:\/\/id.eaufrance.fr\/StationMesureEauxSurface\/04043800",
        "longitude": 3.211251384,
        "latitude": 46.536002961,
        "code_commune": "03275",
        "libelle_commune": "Souvigny",
        "code_cours_eau": "K3464000",
        "libelle_cours_eau": "la Queune",
        "uri_cours_eau": "https:\/\/id.eaufrance.fr\/CoursEau_Carthage2017\/K3464000",
        "date_mesure_temp": "2015-08-01",
        "heure_mesure_temp": "00:19:28",
        "resultat": 15.4849996566772
    },
    {
        "code_station": "04043800",
        "libelle_station": "QUEUNE \u00e0 SOUVIGNY",
        "localisation": "PRELEVEMENT EN AVAL DE LA PASSERELLE ET DU GUE",
        "uri_station": "https:\/\/id.eaufrance.fr\/StationMesureEauxSurface\/04043800",
        "longitude": 3.211251384,
        "latitude": 46.536002961,
        "code_commune": "03275",
        "libelle_commune": "Souvigny",
        "code_cours_eau": "K3464000",
        "libelle_cours_eau": "la Queune",
        "uri_cours_eau": "https:\/\/id.eaufrance.fr\/CoursEau_Carthage2017\/K3464000",
        "date_mesure_temp": "2015-09-01",
        "heure_mesure_temp": "00:19:28",
        "resultat": 17.9860000610352
    },
    {
        "code_station": "04043800",
        "libelle_station": "QUEUNE \u00e0 SOUVIGNY",
        "localisation": "PRELEVEMENT EN AVAL DE LA PASSERELLE ET DU GUE",
        "uri_station": "https:\/\/id.eaufrance.fr\/StationMesureEauxSurface\/04043800",
        "longitude": 3.211251384,
        "latitude": 46.536002961,
        "code_commune": "03275",
        "libelle_commune": "Souvigny",
        "code_cours_eau": "K3464000",
        "libelle_cours_eau": "la Queune",
        "uri_cours_eau": "https:\/\/id.eaufrance.fr\/CoursEau_Carthage2017\/K3464000",
        "date_mesure_temp": "2015-10-01",
        "heure_mesure_temp": "00:19:28",
        "resultat": 10.6630001068115
    },
    {
        "code_station": "04043800",
        "libelle_station": "QUEUNE \u00e0 SOUVIGNY",
        "localisation": "PRELEVEMENT EN AVAL DE LA PASSERELLE ET DU GUE",
        "uri_station": "https:\/\/id.eaufrance.fr\/StationMesureEauxSurface\/04043800",
        "longitude": 3.211251384,
        "latitude": 46.536002961,
        "code_commune": "03275",
        "libelle_commune": "Souvigny",
        "code_cours_eau": "K3464000",
        "libelle_cours_eau": "la Queune",
        "uri_cours_eau": "https:\/\/id.eaufrance.fr\/CoursEau_Carthage2017\/K3464000",
        "date_mesure_temp": "2015-11-01",
        "heure_mesure_temp": "00:19:28",
        "resultat": 9.75599956512451
    },
    {
        "code_station": "04043800",
        "libelle_station": "QUEUNE \u00e0 SOUVIGNY",
        "localisation": "PRELEVEMENT EN AVAL DE LA PASSERELLE ET DU GUE",
        "uri_station": "https:\/\/id.eaufrance.fr\/StationMesureEauxSurface\/04043800",
        "longitude": 3.211251384,
        "latitude": 46.536002961,
        "code_commune": "03275",
        "libelle_commune": "Souvigny",
        "code_cours_eau": "K3464000",
        "libelle_cours_eau": "la Queune",
        "uri_cours_eau": "https:\/\/id.eaufrance.fr\/CoursEau_Carthage2017\/K3464000",
        "date_mesure_temp": "2015-12-01",
        "heure_mesure_temp": "00:19:28",
        "resultat": 8.29500007629395
    }
]